{
"meta":{"test_sets":[],"test_metrics":[],"learn_metrics":[{"best_value":"Min","name":"RMSE"}],"launch_mode":"Train","parameters":"","iteration_count":1000,"learn_sets":["learn"],"name":"experiment"},
"iterations":[
{"learn":[14.61268541],"iteration":0,"passed_time":0.1648293275,"remaining_time":164.6644982},
{"learn":[14.23196558],"iteration":1,"passed_time":0.1673385977,"remaining_time":83.50196023},
{"learn":[13.86674177],"iteration":2,"passed_time":0.1691833498,"remaining_time":56.2252666},
{"learn":[13.49946468],"iteration":3,"passed_time":0.1709251954,"remaining_time":42.56037365},
{"learn":[13.16661202],"iteration":4,"passed_time":0.1726316518,"remaining_time":34.35369871},
{"learn":[12.85632158],"iteration":5,"passed_time":0.1741677374,"remaining_time":28.85378849},
{"learn":[12.56784336],"iteration":6,"passed_time":0.175950017,"remaining_time":24.95976669},
{"learn":[12.31617801],"iteration":7,"passed_time":0.177368314,"remaining_time":21.99367093},
{"learn":[12.01509946],"iteration":8,"passed_time":0.1789597291,"remaining_time":19.70545462},
{"learn":[11.71512571],"iteration":9,"passed_time":0.1804452503,"remaining_time":17.86407978},
{"learn":[11.43264457],"iteration":10,"passed_time":0.1821680715,"remaining_time":16.3785657},
{"learn":[11.17973129],"iteration":11,"passed_time":0.1838356344,"remaining_time":15.13580057},
{"learn":[10.93746433],"iteration":12,"passed_time":0.1855374219,"remaining_time":14.08657195},
{"learn":[10.69387075],"iteration":13,"passed_time":0.1869416228,"remaining_time":13.16603144},
{"learn":[10.4615922],"iteration":14,"passed_time":0.1884452477,"remaining_time":12.37457127},
{"learn":[10.2299235],"iteration":15,"passed_time":0.1900053424,"remaining_time":11.68532856},
{"learn":[10.01419731],"iteration":16,"passed_time":0.1914793017,"remaining_time":11.07200903},
{"learn":[9.795856918],"iteration":17,"passed_time":0.1928945139,"remaining_time":10.52346737},
{"learn":[9.60040151],"iteration":18,"passed_time":0.1942184936,"remaining_time":10.02780749},
{"learn":[9.418664989],"iteration":19,"passed_time":0.1961008889,"remaining_time":9.608943554},
{"learn":[9.249278645],"iteration":20,"passed_time":0.1975560779,"remaining_time":9.209876201},
{"learn":[9.090113396],"iteration":21,"passed_time":0.1990517222,"remaining_time":8.84875383},
{"learn":[8.909548708],"iteration":22,"passed_time":0.2005450279,"remaining_time":8.518804013},
{"learn":[8.740140208],"iteration":23,"passed_time":0.2019824563,"remaining_time":8.213953221},
{"learn":[8.59377682],"iteration":24,"passed_time":0.2034857068,"remaining_time":7.935942566},
{"learn":[8.453885414],"iteration":25,"passed_time":0.2047080207,"remaining_time":7.668677391},
{"learn":[8.317732234],"iteration":26,"passed_time":0.2062774735,"remaining_time":7.433628951},
{"learn":[8.180896085],"iteration":27,"passed_time":0.2078244052,"remaining_time":7.214475779},
{"learn":[8.053220863],"iteration":28,"passed_time":0.2092469808,"remaining_time":7.00616615},
{"learn":[7.924234474],"iteration":29,"passed_time":0.2110949336,"remaining_time":6.825402852},
{"learn":[7.818879511],"iteration":30,"passed_time":0.2128504836,"remaining_time":6.653294148},
{"learn":[7.719346395],"iteration":31,"passed_time":0.2145337673,"remaining_time":6.48964646},
{"learn":[7.624163594],"iteration":32,"passed_time":0.2159273461,"remaining_time":6.327325567},
{"learn":[7.524952543],"iteration":33,"passed_time":0.2175600378,"remaining_time":6.181264603},
{"learn":[7.424464745],"iteration":34,"passed_time":0.2192007461,"remaining_time":6.043677714},
{"learn":[7.327482321],"iteration":35,"passed_time":0.2207168443,"remaining_time":5.910306607},
{"learn":[7.238666841],"iteration":36,"passed_time":0.222364108,"remaining_time":5.78747665},
{"learn":[7.158842395],"iteration":37,"passed_time":0.2240311279,"remaining_time":5.67152487},
{"learn":[7.074348246],"iteration":38,"passed_time":0.225950604,"remaining_time":5.567654626},
{"learn":[6.992269093],"iteration":39,"passed_time":0.2275363289,"remaining_time":5.460871895},
{"learn":[6.925219745],"iteration":40,"passed_time":0.2291671678,"remaining_time":5.360275949},
{"learn":[6.86013671],"iteration":41,"passed_time":0.230965914,"remaining_time":5.268222514},
{"learn":[6.786739622],"iteration":42,"passed_time":0.2325973548,"remaining_time":5.176643455},
{"learn":[6.73057926],"iteration":43,"passed_time":0.2342596428,"remaining_time":5.089823148},
{"learn":[6.666356486],"iteration":44,"passed_time":0.2359648588,"remaining_time":5.00769867},
{"learn":[6.606182832],"iteration":45,"passed_time":0.2374878671,"remaining_time":4.925291853},
{"learn":[6.547854615],"iteration":46,"passed_time":0.2391204241,"remaining_time":4.848548174},
{"learn":[6.49240675],"iteration":47,"passed_time":0.2406992514,"remaining_time":4.773868485},
{"learn":[6.431317261],"iteration":48,"passed_time":0.2420979393,"remaining_time":4.698676332},
{"learn":[6.377586395],"iteration":49,"passed_time":0.2438078272,"remaining_time":4.632348716},
{"learn":[6.327558015],"iteration":50,"passed_time":0.2453408444,"remaining_time":4.565263948},
{"learn":[6.282040317],"iteration":51,"passed_time":0.2468168195,"remaining_time":4.499660479},
{"learn":[6.237655841],"iteration":52,"passed_time":0.2484916168,"remaining_time":4.440029455},
{"learn":[6.192792003],"iteration":53,"passed_time":0.2498510189,"remaining_time":4.377019702},
{"learn":[6.150579347],"iteration":54,"passed_time":0.2513286993,"remaining_time":4.318284016},
{"learn":[6.115693845],"iteration":55,"passed_time":0.2530963575,"remaining_time":4.266481455},
{"learn":[6.078780782],"iteration":56,"passed_time":0.254722141,"remaining_time":4.214087351},
{"learn":[6.045146957],"iteration":57,"passed_time":0.2563830191,"remaining_time":4.164013861},
{"learn":[6.008080327],"iteration":58,"passed_time":0.257811149,"remaining_time":4.111869343},
{"learn":[5.977575734],"iteration":59,"passed_time":0.2593759139,"remaining_time":4.063555985},
{"learn":[5.948036502],"iteration":60,"passed_time":0.2609755442,"remaining_time":4.017312065},
{"learn":[5.914888282],"iteration":61,"passed_time":0.2624937913,"remaining_time":3.971277036},
{"learn":[5.884957796],"iteration":62,"passed_time":0.2639683124,"remaining_time":3.9260049},
{"learn":[5.849539885],"iteration":63,"passed_time":0.2655517622,"remaining_time":3.883694522},
{"learn":[5.821387627],"iteration":64,"passed_time":0.2670517008,"remaining_time":3.841436003},
{"learn":[5.797012279],"iteration":65,"passed_time":0.2687848115,"remaining_time":3.803712332},
{"learn":[5.768685095],"iteration":66,"passed_time":0.2702848619,"remaining_time":3.763817554},
{"learn":[5.755484587],"iteration":67,"passed_time":0.2710824899,"remaining_time":3.715424715},
{"learn":[5.731887055],"iteration":68,"passed_time":0.2726633828,"remaining_time":3.678979846},
{"learn":[5.707148487],"iteration":69,"passed_time":0.2742947952,"remaining_time":3.644202279},
{"learn":[5.685365039],"iteration":70,"passed_time":0.2759685625,"remaining_time":3.610912599},
{"learn":[5.663541834],"iteration":71,"passed_time":0.2774758216,"remaining_time":3.576355034},
{"learn":[5.638108797],"iteration":72,"passed_time":0.2791096639,"remaining_time":3.544310389},
{"learn":[5.619204893],"iteration":73,"passed_time":0.2806519466,"remaining_time":3.511941926},
{"learn":[5.598472793],"iteration":74,"passed_time":0.2827922381,"remaining_time":3.487770936},
{"learn":[5.577007075],"iteration":75,"passed_time":0.2844274706,"remaining_time":3.458039248},
{"learn":[5.562637084],"iteration":76,"passed_time":0.2859454276,"remaining_time":3.427631554},
{"learn":[5.54729991],"iteration":77,"passed_time":0.2873973038,"remaining_time":3.397183514},
{"learn":[5.530737623],"iteration":78,"passed_time":0.2889030315,"remaining_time":3.368097368},
{"learn":[5.513704873],"iteration":79,"passed_time":0.2903050274,"remaining_time":3.338507816},
{"learn":[5.501575529],"iteration":80,"passed_time":0.2917704791,"remaining_time":3.310334201},
{"learn":[5.484080734],"iteration":81,"passed_time":0.2931569867,"remaining_time":3.281928217},
{"learn":[5.472178894],"iteration":82,"passed_time":0.2947514209,"remaining_time":3.256470517},
{"learn":[5.458923342],"iteration":83,"passed_time":0.2962427448,"remaining_time":3.230456598},
{"learn":[5.451382371],"iteration":84,"passed_time":0.2973531879,"remaining_time":3.200919611},
{"learn":[5.441410748],"iteration":85,"passed_time":0.2989899927,"remaining_time":3.17763783},
{"learn":[5.434047468],"iteration":86,"passed_time":0.3000218546,"remaining_time":3.148505209},
{"learn":[5.422107497],"iteration":87,"passed_time":0.3016693961,"remaining_time":3.126391923},
{"learn":[5.40731265],"iteration":88,"passed_time":0.3033225428,"remaining_time":3.104795916},
{"learn":[5.396360181],"iteration":89,"passed_time":0.3047784612,"remaining_time":3.081648885},
{"learn":[5.383793239],"iteration":90,"passed_time":0.3062536079,"remaining_time":3.059170655},
{"learn":[5.369605034],"iteration":91,"passed_time":0.3076854038,"remaining_time":3.036721159},
{"learn":[5.357467333],"iteration":92,"passed_time":0.3093060686,"remaining_time":3.016565637},
{"learn":[5.341109968],"iteration":93,"passed_time":0.3108415394,"remaining_time":2.995983347},
{"learn":[5.330529276],"iteration":94,"passed_time":0.3123471192,"remaining_time":2.975517294},
{"learn":[5.319862075],"iteration":95,"passed_time":0.3138779903,"remaining_time":2.955684409},
{"learn":[5.313052243],"iteration":96,"passed_time":0.3153327942,"remaining_time":2.935520754},
{"learn":[5.299677207],"iteration":97,"passed_time":0.3170005816,"remaining_time":2.91769923},
{"learn":[5.287546698],"iteration":98,"passed_time":0.3184204352,"remaining_time":2.897947597},
{"learn":[5.279803754],"iteration":99,"passed_time":0.3199807134,"remaining_time":2.879826421},
{"learn":[5.272254612],"iteration":100,"passed_time":0.3214522904,"remaining_time":2.861243655},
{"learn":[5.268813888],"iteration":101,"passed_time":0.3223277071,"remaining_time":2.837747853},
{"learn":[5.258113767],"iteration":102,"passed_time":0.3237614647,"remaining_time":2.819553727},
{"learn":[5.251018576],"iteration":103,"passed_time":0.325285778,"remaining_time":2.802462087},
{"learn":[5.24171237],"iteration":104,"passed_time":0.3271046963,"remaining_time":2.788178125},
{"learn":[5.233984943],"iteration":105,"passed_time":0.3288692577,"remaining_time":2.773670909},
{"learn":[5.226240449],"iteration":106,"passed_time":0.3306301396,"remaining_time":2.759371165},
{"learn":[5.220541644],"iteration":107,"passed_time":0.3321888103,"remaining_time":2.743633507},
{"learn":[5.211712096],"iteration":108,"passed_time":0.3340874313,"remaining_time":2.730934874},
{"learn":[5.203388597],"iteration":109,"passed_time":0.3359521055,"remaining_time":2.718157945},
{"learn":[5.196026544],"iteration":110,"passed_time":0.3375394448,"remaining_time":2.703356454},
{"learn":[5.188716772],"iteration":111,"passed_time":0.3391627375,"remaining_time":2.68907599},
{"learn":[5.182163132],"iteration":112,"passed_time":0.3408059591,"remaining_time":2.67517598},
{"learn":[5.17764747],"iteration":113,"passed_time":0.3423451795,"remaining_time":2.660682711},
{"learn":[5.170548056],"iteration":114,"passed_time":0.3438450483,"remaining_time":2.646111894},
{"learn":[5.165901827],"iteration":115,"passed_time":0.3451312764,"remaining_time":2.630138348},
{"learn":[5.160333668],"iteration":116,"passed_time":0.3467222359,"remaining_time":2.616715677},
{"learn":[5.148953243],"iteration":117,"passed_time":0.3482287395,"remaining_time":2.602862273},
{"learn":[5.144729126],"iteration":118,"passed_time":0.3495101847,"remaining_time":2.587550191},
{"learn":[5.139939946],"iteration":119,"passed_time":0.3509847636,"remaining_time":2.573888266},
{"learn":[5.132898872],"iteration":120,"passed_time":0.3524626917,"remaining_time":2.560452115},
{"learn":[5.129073077],"iteration":121,"passed_time":0.3539532389,"remaining_time":2.547302818},
{"learn":[5.127123916],"iteration":122,"passed_time":0.3547219977,"remaining_time":2.529196683},
{"learn":[5.121282057],"iteration":123,"passed_time":0.3562534054,"remaining_time":2.516757928},
{"learn":[5.114489821],"iteration":124,"passed_time":0.3576170401,"remaining_time":2.50331928},
{"learn":[5.107777291],"iteration":125,"passed_time":0.3591264846,"remaining_time":2.491083711},
{"learn":[5.103518754],"iteration":126,"passed_time":0.3606940569,"remaining_time":2.479416628},
{"learn":[5.101133351],"iteration":127,"passed_time":0.3616219745,"remaining_time":2.463549701},
{"learn":[5.096462705],"iteration":128,"passed_time":0.3630182394,"remaining_time":2.45107664},
{"learn":[5.08562082],"iteration":129,"passed_time":0.3644676504,"remaining_time":2.439129661},
{"learn":[5.080483682],"iteration":130,"passed_time":0.3658829428,"remaining_time":2.427116621},
{"learn":[5.07437499],"iteration":131,"passed_time":0.3673322717,"remaining_time":2.415487968},
{"learn":[5.070683732],"iteration":132,"passed_time":0.3689440486,"remaining_time":2.405071354},
{"learn":[5.06432037],"iteration":133,"passed_time":0.370393642,"remaining_time":2.393738014},
{"learn":[5.057436484],"iteration":134,"passed_time":0.3718796749,"remaining_time":2.382784584},
{"learn":[5.053254656],"iteration":135,"passed_time":0.3734120697,"remaining_time":2.372264914},
{"learn":[5.04801663],"iteration":136,"passed_time":0.3749319568,"remaining_time":2.361797655},
{"learn":[5.045680836],"iteration":137,"passed_time":0.3762529163,"remaining_time":2.350217492},
{"learn":[5.041857933],"iteration":138,"passed_time":0.3777197406,"remaining_time":2.339688465},
{"learn":[5.035264888],"iteration":139,"passed_time":0.3790955103,"remaining_time":2.328729563},
{"learn":[5.028771948],"iteration":140,"passed_time":0.3806972353,"remaining_time":2.319283157},
{"learn":[5.024912247],"iteration":141,"passed_time":0.3821380798,"remaining_time":2.308975158},
{"learn":[5.02239068],"iteration":142,"passed_time":0.383730206,"remaining_time":2.299697808},
{"learn":[5.017110572],"iteration":143,"passed_time":0.3851708862,"remaining_time":2.289626934},
{"learn":[5.010707886],"iteration":144,"passed_time":0.3866075682,"remaining_time":2.279651523},
{"learn":[5.004389868],"iteration":145,"passed_time":0.3882408843,"remaining_time":2.270943255},
{"learn":[4.997628683],"iteration":146,"passed_time":0.3896378465,"remaining_time":2.260959749},
{"learn":[4.991497851],"iteration":147,"passed_time":0.3911065351,"remaining_time":2.251505189},
{"learn":[4.988345253],"iteration":148,"passed_time":0.3925776685,"remaining_time":2.242171785},
{"learn":[4.98460423],"iteration":149,"passed_time":0.3940617489,"remaining_time":2.233016577},
{"learn":[4.982441783],"iteration":150,"passed_time":0.3955561107,"remaining_time":2.224020781},
{"learn":[4.977461771],"iteration":151,"passed_time":0.3969776447,"remaining_time":2.214717386},
{"learn":[4.973601586],"iteration":152,"passed_time":0.3985084625,"remaining_time":2.206122012},
{"learn":[4.968328804],"iteration":153,"passed_time":0.4000399424,"remaining_time":2.197622021},
{"learn":[4.9640736],"iteration":154,"passed_time":0.4015025333,"remaining_time":2.188836391},
{"learn":[4.960865882],"iteration":155,"passed_time":0.4029828969,"remaining_time":2.180240801},
{"learn":[4.957014156],"iteration":156,"passed_time":0.4044998062,"remaining_time":2.171932081},
{"learn":[4.952244852],"iteration":157,"passed_time":0.4059252057,"remaining_time":2.163221666},
{"learn":[4.949695675],"iteration":158,"passed_time":0.4073550382,"remaining_time":2.154626334},
{"learn":[4.946584698],"iteration":159,"passed_time":0.4088520391,"remaining_time":2.146473205},
{"learn":[4.940192834],"iteration":160,"passed_time":0.4102977742,"remaining_time":2.138135606},
{"learn":[4.936727994],"iteration":161,"passed_time":0.4117089928,"remaining_time":2.129704543},
{"learn":[4.932342063],"iteration":162,"passed_time":0.4133888138,"remaining_time":2.122738878},
{"learn":[4.925830838],"iteration":163,"passed_time":0.414947103,"remaining_time":2.115218159},
{"learn":[4.922571773],"iteration":164,"passed_time":0.4166978633,"remaining_time":2.108743733},
{"learn":[4.918395814],"iteration":165,"passed_time":0.4182102327,"remaining_time":2.101128519},
{"learn":[4.911142452],"iteration":166,"passed_time":0.419685278,"remaining_time":2.093400219},
{"learn":[4.908276131],"iteration":167,"passed_time":0.4211662376,"remaining_time":2.085775653},
{"learn":[4.904584645],"iteration":168,"passed_time":0.4226376275,"remaining_time":2.078176736},
{"learn":[4.89795517],"iteration":169,"passed_time":0.4242865308,"remaining_time":2.071516592},
{"learn":[4.895556491],"iteration":170,"passed_time":0.4260799663,"remaining_time":2.065615743},
{"learn":[4.890591233],"iteration":171,"passed_time":0.4274796354,"remaining_time":2.057867082},
{"learn":[4.884629277],"iteration":172,"passed_time":0.4289436418,"remaining_time":2.050499374},
{"learn":[4.880550786],"iteration":173,"passed_time":0.4304422293,"remaining_time":2.043363686},
{"learn":[4.876384842],"iteration":174,"passed_time":0.4319168935,"remaining_time":2.036179641},
{"learn":[4.872638238],"iteration":175,"passed_time":0.4336445437,"remaining_time":2.030244909},
{"learn":[4.869137118],"iteration":176,"passed_time":0.4351509263,"remaining_time":2.023328883},
{"learn":[4.863587157],"iteration":177,"passed_time":0.4366630019,"remaining_time":2.01649993},
{"learn":[4.858028614],"iteration":178,"passed_time":0.4382786723,"remaining_time":2.01020553},
{"learn":[4.853838176],"iteration":179,"passed_time":0.4398546749,"remaining_time":2.003782408},
{"learn":[4.853462329],"iteration":180,"passed_time":0.4406662431,"remaining_time":1.993953885},
{"learn":[4.851573196],"iteration":181,"passed_time":0.4421009097,"remaining_time":1.987024968},
{"learn":[4.848442087],"iteration":182,"passed_time":0.443516358,"remaining_time":1.980070298},
{"learn":[4.845547104],"iteration":183,"passed_time":0.4450449968,"remaining_time":1.973677812},
{"learn":[4.839868817],"iteration":184,"passed_time":0.4465182182,"remaining_time":1.967093772},
{"learn":[4.836336958],"iteration":185,"passed_time":0.4480546344,"remaining_time":1.960841249},
{"learn":[4.831124789],"iteration":186,"passed_time":0.4496882129,"remaining_time":1.955061589},
{"learn":[4.827407333],"iteration":187,"passed_time":0.4511140052,"remaining_time":1.948428575},
{"learn":[4.824088918],"iteration":188,"passed_time":0.4527242903,"remaining_time":1.942642325},
{"learn":[4.820934539],"iteration":189,"passed_time":0.4546332361,"remaining_time":1.938173269},
{"learn":[4.816975227],"iteration":190,"passed_time":0.4564446134,"remaining_time":1.93331776},
{"learn":[4.812340486],"iteration":191,"passed_time":0.4582109963,"remaining_time":1.92830461},
{"learn":[4.806402747],"iteration":192,"passed_time":0.4598398694,"remaining_time":1.922750127},
{"learn":[4.801521788],"iteration":193,"passed_time":0.4614372817,"remaining_time":1.917105408},
{"learn":[4.797601172],"iteration":194,"passed_time":0.462991334,"remaining_time":1.911323199},
{"learn":[4.792694629],"iteration":195,"passed_time":0.4644821241,"remaining_time":1.905324631},
{"learn":[4.789794613],"iteration":196,"passed_time":0.4659127841,"remaining_time":1.899126729},
{"learn":[4.785367055],"iteration":197,"passed_time":0.4675397359,"remaining_time":1.893772062},
{"learn":[4.780376856],"iteration":198,"passed_time":0.468997027,"remaining_time":1.887771953},
{"learn":[4.776691261],"iteration":199,"passed_time":0.470493791,"remaining_time":1.881975164},
{"learn":[4.773470753],"iteration":200,"passed_time":0.4721204815,"remaining_time":1.876737635},
{"learn":[4.77207327],"iteration":201,"passed_time":0.4735371164,"remaining_time":1.870706034},
{"learn":[4.767347177],"iteration":202,"passed_time":0.4750337991,"remaining_time":1.865034177},
{"learn":[4.763983068],"iteration":203,"passed_time":0.4764401831,"remaining_time":1.859050911},
{"learn":[4.761588849],"iteration":204,"passed_time":0.4780826128,"remaining_time":1.854027693},
{"learn":[4.758558086],"iteration":205,"passed_time":0.4795605156,"remaining_time":1.848403152},
{"learn":[4.753678804],"iteration":206,"passed_time":0.4810227582,"remaining_time":1.842758682},
{"learn":[4.746510889],"iteration":207,"passed_time":0.4828961681,"remaining_time":1.838720025},
{"learn":[4.744840601],"iteration":208,"passed_time":0.4845519568,"remaining_time":1.833878458},
{"learn":[4.741702222],"iteration":209,"passed_time":0.4860674445,"remaining_time":1.828539434},
{"learn":[4.739352853],"iteration":210,"passed_time":0.487770902,"remaining_time":1.823939534},
{"learn":[4.735539287],"iteration":211,"passed_time":0.4893931174,"remaining_time":1.819064984},
{"learn":[4.730726751],"iteration":212,"passed_time":0.490940827,"remaining_time":1.813945685},
{"learn":[4.726416092],"iteration":213,"passed_time":0.4925603027,"remaining_time":1.809123355},
{"learn":[4.721293082],"iteration":214,"passed_time":0.4940295933,"remaining_time":1.803782469},
{"learn":[4.718443695],"iteration":215,"passed_time":0.4954275354,"remaining_time":1.798218462},
{"learn":[4.711627962],"iteration":216,"passed_time":0.4970264042,"remaining_time":1.793417855},
{"learn":[4.709790764],"iteration":217,"passed_time":0.4986046435,"remaining_time":1.78857262},
{"learn":[4.706913073],"iteration":218,"passed_time":0.5001878564,"remaining_time":1.783774958},
{"learn":[4.703846389],"iteration":219,"passed_time":0.501616073,"remaining_time":1.778456986},
{"learn":[4.701001135],"iteration":220,"passed_time":0.5030919635,"remaining_time":1.773342261},
{"learn":[4.700380864],"iteration":221,"passed_time":0.5045213832,"remaining_time":1.76809746},
{"learn":[4.695837486],"iteration":222,"passed_time":0.5059581174,"remaining_time":1.762912364},
{"learn":[4.691242996],"iteration":223,"passed_time":0.5073772163,"remaining_time":1.757699642},
{"learn":[4.690284609],"iteration":224,"passed_time":0.5088870356,"remaining_time":1.752833122},
{"learn":[4.68827119],"iteration":225,"passed_time":0.5103886798,"remaining_time":1.747968311},
{"learn":[4.686922425],"iteration":226,"passed_time":0.511868205,"remaining_time":1.743057808},
{"learn":[4.686085874],"iteration":227,"passed_time":0.5133215917,"remaining_time":1.738088898},
{"learn":[4.683230741],"iteration":228,"passed_time":0.5147334743,"remaining_time":1.733010955},
{"learn":[4.6773487],"iteration":229,"passed_time":0.5161608681,"remaining_time":1.728016819},
{"learn":[4.671462906],"iteration":230,"passed_time":0.5175373696,"remaining_time":1.722884144},
{"learn":[4.664799601],"iteration":231,"passed_time":0.5191507055,"remaining_time":1.718567853},
{"learn":[4.660979386],"iteration":232,"passed_time":0.5206853631,"remaining_time":1.714015766},
{"learn":[4.656281279],"iteration":233,"passed_time":0.5221193043,"remaining_time":1.709159774},
{"learn":[4.651997094],"iteration":234,"passed_time":0.5236831658,"remaining_time":1.704755838},
{"learn":[4.650151977],"iteration":235,"passed_time":0.5253377497,"remaining_time":1.700669664},
{"learn":[4.648478046],"iteration":236,"passed_time":0.526755575,"remaining_time":1.695841788},
{"learn":[4.646364602],"iteration":237,"passed_time":0.5282941626,"remaining_time":1.69142921},
{"learn":[4.642635873],"iteration":238,"passed_time":0.5298083543,"remaining_time":1.686963003},
{"learn":[4.640860821],"iteration":239,"passed_time":0.5312936614,"remaining_time":1.682429928},
{"learn":[4.639446822],"iteration":240,"passed_time":0.532680476,"remaining_time":1.677611956},
{"learn":[4.637120072],"iteration":241,"passed_time":0.5340530275,"remaining_time":1.672777665},
{"learn":[4.633769267],"iteration":242,"passed_time":0.535544121,"remaining_time":1.668341151},
{"learn":[4.630491517],"iteration":243,"passed_time":0.5371156149,"remaining_time":1.664177889},
{"learn":[4.627813333],"iteration":244,"passed_time":0.5386140314,"remaining_time":1.659810586},
{"learn":[4.622496304],"iteration":245,"passed_time":0.5402479698,"remaining_time":1.655881989},
{"learn":[4.618979301],"iteration":246,"passed_time":0.5416748874,"remaining_time":1.651340851},
{"learn":[4.616563458],"iteration":247,"passed_time":0.5432874045,"remaining_time":1.647387614},
{"learn":[4.614759385],"iteration":248,"passed_time":0.5446242928,"remaining_time":1.642621863},
{"learn":[4.61251363],"iteration":249,"passed_time":0.5459884376,"remaining_time":1.637965313},
{"learn":[4.608796693],"iteration":250,"passed_time":0.5475174143,"remaining_time":1.633826866},
{"learn":[4.60847774],"iteration":251,"passed_time":0.5489916877,"remaining_time":1.629546756},
{"learn":[4.605195659],"iteration":252,"passed_time":0.5503854064,"remaining_time":1.625050983},
{"learn":[4.60103766],"iteration":253,"passed_time":0.5519578089,"remaining_time":1.621104431},
{"learn":[4.599325598],"iteration":254,"passed_time":0.553379977,"remaining_time":1.61673758},
{"learn":[4.597012808],"iteration":255,"passed_time":0.5549483801,"remaining_time":1.61281873},
{"learn":[4.594161533],"iteration":256,"passed_time":0.5565725866,"remaining_time":1.609079501},
{"learn":[4.592197259],"iteration":257,"passed_time":0.5580312266,"remaining_time":1.604880504},
{"learn":[4.58952828],"iteration":258,"passed_time":0.5594984497,"remaining_time":1.600727225},
{"learn":[4.585816572],"iteration":259,"passed_time":0.5609418371,"remaining_time":1.596526767},
{"learn":[4.582934052],"iteration":260,"passed_time":0.5625243583,"remaining_time":1.592741382},
{"learn":[4.582234842],"iteration":261,"passed_time":0.5639140272,"remaining_time":1.588429588},
{"learn":[4.57571562],"iteration":262,"passed_time":0.5652382502,"remaining_time":1.583956617},
{"learn":[4.571197349],"iteration":263,"passed_time":0.5668325132,"remaining_time":1.58026034},
{"learn":[4.56723703],"iteration":264,"passed_time":0.5686148121,"remaining_time":1.57710146},
{"learn":[4.560335567],"iteration":265,"passed_time":0.5702572738,"remaining_time":1.573567064},
{"learn":[4.554709345],"iteration":266,"passed_time":0.5716628366,"remaining_time":1.569396476},
{"learn":[4.552806306],"iteration":267,"passed_time":0.5730860651,"remaining_time":1.565294775},
{"learn":[4.550766241],"iteration":268,"passed_time":0.5744458575,"remaining_time":1.561040602},
{"learn":[4.549216045],"iteration":269,"passed_time":0.5760154538,"remaining_time":1.557375116},
{"learn":[4.547687452],"iteration":270,"passed_time":0.5775878262,"remaining_time":1.553732566},
{"learn":[4.545642435],"iteration":271,"passed_time":0.5789736509,"remaining_time":1.549605948},
{"learn":[4.543930359],"iteration":272,"passed_time":0.5803779452,"remaining_time":1.545548594},
{"learn":[4.541029943],"iteration":273,"passed_time":0.5819158708,"remaining_time":1.541864679},
{"learn":[4.537781449],"iteration":274,"passed_time":0.5833921994,"remaining_time":1.53803398},
{"learn":[4.53066128],"iteration":275,"passed_time":0.5849285418,"remaining_time":1.534377769},
{"learn":[4.526763956],"iteration":276,"passed_time":0.5865179291,"remaining_time":1.530875317},
{"learn":[4.522036004],"iteration":277,"passed_time":0.5879929736,"remaining_time":1.527089665},
{"learn":[4.515307629],"iteration":278,"passed_time":0.5894388069,"remaining_time":1.523245089},
{"learn":[4.51109143],"iteration":279,"passed_time":0.5908933663,"remaining_time":1.519440085},
{"learn":[4.508233494],"iteration":280,"passed_time":0.5923226834,"remaining_time":1.515587222},
{"learn":[4.502555629],"iteration":281,"passed_time":0.5938690387,"remaining_time":1.512049538},
{"learn":[4.500081355],"iteration":282,"passed_time":0.5953789309,"remaining_time":1.508433546},
{"learn":[4.495281743],"iteration":283,"passed_time":0.5968694894,"remaining_time":1.504783642},
{"learn":[4.492138869],"iteration":284,"passed_time":0.5983661324,"remaining_time":1.501164157},
{"learn":[4.491708261],"iteration":285,"passed_time":0.5998264189,"remaining_time":1.497468752},
{"learn":[4.489398865],"iteration":286,"passed_time":0.601289021,"remaining_time":1.493794676},
{"learn":[4.485796373],"iteration":287,"passed_time":0.6027616172,"remaining_time":1.490160665},
{"learn":[4.479542205],"iteration":288,"passed_time":0.6041852729,"remaining_time":1.486421208},
{"learn":[4.475986993],"iteration":289,"passed_time":0.6056921733,"remaining_time":1.482901528},
{"learn":[4.468661855],"iteration":290,"passed_time":0.6071728251,"remaining_time":1.479331728},
{"learn":[4.463785664],"iteration":291,"passed_time":0.6087122034,"remaining_time":1.47591863},
{"learn":[4.460445831],"iteration":292,"passed_time":0.6100894103,"remaining_time":1.472127007},
{"learn":[4.45692492],"iteration":293,"passed_time":0.6116398684,"remaining_time":1.468767847},
{"learn":[4.454031688],"iteration":294,"passed_time":0.6131423002,"remaining_time":1.465306175},
{"learn":[4.451672391],"iteration":295,"passed_time":0.6145697272,"remaining_time":1.461679351},
{"learn":[4.45031553],"iteration":296,"passed_time":0.6160537114,"remaining_time":1.458201209},
{"learn":[4.446782666],"iteration":297,"passed_time":0.6176354046,"remaining_time":1.454966624},
{"learn":[4.444369689],"iteration":298,"passed_time":0.6189995458,"remaining_time":1.451233049},
{"learn":[4.44411683],"iteration":299,"passed_time":0.6204874548,"remaining_time":1.447804061},
{"learn":[4.440876943],"iteration":300,"passed_time":0.6219160035,"remaining_time":1.444250121},
{"learn":[4.439336453],"iteration":301,"passed_time":0.6232811271,"remaining_time":1.440563665},
{"learn":[4.436666901],"iteration":302,"passed_time":0.6247639771,"remaining_time":1.43716334},
{"learn":[4.433043336],"iteration":303,"passed_time":0.6262564044,"remaining_time":1.433797557},
{"learn":[4.431419305],"iteration":304,"passed_time":0.6278137606,"remaining_time":1.430592012},
{"learn":[4.428859646],"iteration":305,"passed_time":0.6292206776,"remaining_time":1.427056047},
{"learn":[4.424552441],"iteration":306,"passed_time":0.6307095135,"remaining_time":1.423718869},
{"learn":[4.422706391],"iteration":307,"passed_time":0.632061868,"remaining_time":1.420087054},
{"learn":[4.421427994],"iteration":308,"passed_time":0.6335405853,"remaining_time":1.416752571},
{"learn":[4.418733158],"iteration":309,"passed_time":0.6349803421,"remaining_time":1.413343342},
{"learn":[4.415656941],"iteration":310,"passed_time":0.6364242421,"remaining_time":1.409955958},
{"learn":[4.410747417],"iteration":311,"passed_time":0.637874706,"remaining_time":1.406595505},
{"learn":[4.408126521],"iteration":312,"passed_time":0.6393945822,"remaining_time":1.40339961},
{"learn":[4.407843853],"iteration":313,"passed_time":0.640834218,"remaining_time":1.400039088},
{"learn":[4.405219398],"iteration":314,"passed_time":0.6423266309,"remaining_time":1.396805531},
{"learn":[4.402708465],"iteration":315,"passed_time":0.6438916579,"remaining_time":1.393740171},
{"learn":[4.40104971],"iteration":316,"passed_time":0.6454308518,"remaining_time":1.390628618},
{"learn":[4.400830038],"iteration":317,"passed_time":0.6468555396,"remaining_time":1.387281377},
{"learn":[4.39784288],"iteration":318,"passed_time":0.6481850624,"remaining_time":1.383743033},
{"learn":[4.393741845],"iteration":319,"passed_time":0.649607713,"remaining_time":1.38041639},
{"learn":[4.393425936],"iteration":320,"passed_time":0.6510623092,"remaining_time":1.377169184},
{"learn":[4.390505974],"iteration":321,"passed_time":0.6525779341,"remaining_time":1.374061613},
{"learn":[4.390305136],"iteration":322,"passed_time":0.6540360083,"remaining_time":1.370843274},
{"learn":[4.38568203],"iteration":323,"passed_time":0.655513342,"remaining_time":1.367675985},
{"learn":[4.383057135],"iteration":324,"passed_time":0.6571879646,"remaining_time":1.36492885},
{"learn":[4.380662684],"iteration":325,"passed_time":0.6586871898,"remaining_time":1.361825662},
{"learn":[4.37805727],"iteration":326,"passed_time":0.6601591684,"remaining_time":1.358676209},
{"learn":[4.373708319],"iteration":327,"passed_time":0.6616963841,"remaining_time":1.355670641},
{"learn":[4.36887921],"iteration":328,"passed_time":0.6632097795,"remaining_time":1.352625417},
{"learn":[4.367895929],"iteration":329,"passed_time":0.6647012734,"remaining_time":1.34954501},
{"learn":[4.362140573],"iteration":330,"passed_time":0.6662311718,"remaining_time":1.346551825},
{"learn":[4.361931924],"iteration":331,"passed_time":0.6676767919,"remaining_time":1.343397883},
{"learn":[4.359656377],"iteration":332,"passed_time":0.6691589542,"remaining_time":1.340327395},
{"learn":[4.354281355],"iteration":333,"passed_time":0.670662242,"remaining_time":1.337308542},
{"learn":[4.348589447],"iteration":334,"passed_time":0.6722258114,"remaining_time":1.334418402},
{"learn":[4.346355698],"iteration":335,"passed_time":0.6738283425,"remaining_time":1.331613153},
{"learn":[4.343894047],"iteration":336,"passed_time":0.6753025906,"remaining_time":1.328562663},
{"learn":[4.341561356],"iteration":337,"passed_time":0.6768017778,"remaining_time":1.325570346},
{"learn":[4.338869061],"iteration":338,"passed_time":0.678393859,"remaining_time":1.322767967},
{"learn":[4.333720063],"iteration":339,"passed_time":0.6798615357,"remaining_time":1.319731216},
{"learn":[4.330892223],"iteration":340,"passed_time":0.6813899429,"remaining_time":1.316821033},
{"learn":[4.328311474],"iteration":341,"passed_time":0.6829076133,"remaining_time":1.313898273},
{"learn":[4.324580133],"iteration":342,"passed_time":0.6850385547,"remaining_time":1.312158398},
{"learn":[4.323354432],"iteration":343,"passed_time":0.6865673566,"remaining_time":1.309267982},
{"learn":[4.323159553],"iteration":344,"passed_time":0.6881957463,"remaining_time":1.306574533},
{"learn":[4.318639682],"iteration":345,"passed_time":0.6898915947,"remaining_time":1.304014748},
{"learn":[4.312712208],"iteration":346,"passed_time":0.6915623654,"remaining_time":1.301412751},
{"learn":[4.311461062],"iteration":347,"passed_time":0.6932514736,"remaining_time":1.298850462},
{"learn":[4.311178356],"iteration":348,"passed_time":0.694677063,"remaining_time":1.295801628},
{"learn":[4.311102505],"iteration":349,"passed_time":0.6962025986,"remaining_time":1.292947683},
{"learn":[4.310232308],"iteration":350,"passed_time":0.6977399823,"remaining_time":1.290123215},
{"learn":[4.305128197],"iteration":351,"passed_time":0.6992728316,"remaining_time":1.287297713},
{"learn":[4.304595496],"iteration":352,"passed_time":0.7006334224,"remaining_time":1.284163808},
{"learn":[4.3004992],"iteration":353,"passed_time":0.7022063354,"remaining_time":1.28142738},
{"learn":[4.297581524],"iteration":354,"passed_time":0.7037923682,"remaining_time":1.278721345},
{"learn":[4.297355825],"iteration":355,"passed_time":0.7052230647,"remaining_time":1.2757406},
{"learn":[4.295758715],"iteration":356,"passed_time":0.706832477,"remaining_time":1.273090428},
{"learn":[4.292500657],"iteration":357,"passed_time":0.7082858257,"remaining_time":1.270166201},
{"learn":[4.290797586],"iteration":358,"passed_time":0.709806792,"remaining_time":1.267370902},
{"learn":[4.286410608],"iteration":359,"passed_time":0.7112277205,"remaining_time":1.264404836},
{"learn":[4.280278245],"iteration":360,"passed_time":0.7127827879,"remaining_time":1.261684769},
{"learn":[4.279941283],"iteration":361,"passed_time":0.7143549539,"remaining_time":1.259001272},
{"learn":[4.274426275],"iteration":362,"passed_time":0.7158874437,"remaining_time":1.256254275},
{"learn":[4.273567658],"iteration":363,"passed_time":0.7174218236,"remaining_time":1.253517252},
{"learn":[4.269488271],"iteration":364,"passed_time":0.7188725873,"remaining_time":1.25064135},
{"learn":[4.266838205],"iteration":365,"passed_time":0.7202806825,"remaining_time":1.247699324},
{"learn":[4.263456509],"iteration":366,"passed_time":0.7217374165,"remaining_time":1.244849549},
{"learn":[4.260360204],"iteration":367,"passed_time":0.7232360277,"remaining_time":1.242079265},
{"learn":[4.255120549],"iteration":368,"passed_time":0.7247481999,"remaining_time":1.239339063},
{"learn":[4.252582211],"iteration":369,"passed_time":0.7263968837,"remaining_time":1.236837937},
{"learn":[4.247857931],"iteration":370,"passed_time":0.7279271552,"remaining_time":1.234140649},
{"learn":[4.245288911],"iteration":371,"passed_time":0.7294609319,"remaining_time":1.231455552},
{"learn":[4.24048515],"iteration":372,"passed_time":0.7309568062,"remaining_time":1.228712916},
{"learn":[4.2378365],"iteration":373,"passed_time":0.7323791134,"remaining_time":1.22585381},
{"learn":[4.236751063],"iteration":374,"passed_time":0.7339626309,"remaining_time":1.223271051},
{"learn":[4.233240093],"iteration":375,"passed_time":0.7353702965,"remaining_time":1.220401769},
{"learn":[4.230358421],"iteration":376,"passed_time":0.7368292328,"remaining_time":1.217624966},
{"learn":[4.225853583],"iteration":377,"passed_time":0.7382626874,"remaining_time":1.214813205},
{"learn":[4.224702126],"iteration":378,"passed_time":0.7396341031,"remaining_time":1.211907066},
{"learn":[4.224361982],"iteration":379,"passed_time":0.7412552801,"remaining_time":1.20941651},
{"learn":[4.223787954],"iteration":380,"passed_time":0.7427712873,"remaining_time":1.206759651},
{"learn":[4.22144054],"iteration":381,"passed_time":0.7443985934,"remaining_time":1.204288824},
{"learn":[4.217739335],"iteration":382,"passed_time":0.7458922101,"remaining_time":1.201607033},
{"learn":[4.215611665],"iteration":383,"passed_time":0.7473077001,"remaining_time":1.198806102},
{"learn":[4.210236863],"iteration":384,"passed_time":0.7488573302,"remaining_time":1.196226644},
{"learn":[4.208454294],"iteration":385,"passed_time":0.750381831,"remaining_time":1.19361255},
{"learn":[4.207446501],"iteration":386,"passed_time":0.751840457,"remaining_time":1.190899742},
{"learn":[4.204985442],"iteration":387,"passed_time":0.7533598788,"remaining_time":1.188289293},
{"learn":[4.202796622],"iteration":388,"passed_time":0.7549576783,"remaining_time":1.185807562},
{"learn":[4.199774004],"iteration":389,"passed_time":0.7564502274,"remaining_time":1.18316574},
{"learn":[4.199458358],"iteration":390,"passed_time":0.7578401933,"remaining_time":1.18037002},
{"learn":[4.19751254],"iteration":391,"passed_time":0.7594596093,"remaining_time":1.177937353},
{"learn":[4.195201346],"iteration":392,"passed_time":0.7609109361,"remaining_time":1.175249207},
{"learn":[4.190593508],"iteration":393,"passed_time":0.7623944686,"remaining_time":1.172616873},
{"learn":[4.187212054],"iteration":394,"passed_time":0.7638039369,"remaining_time":1.169876916},
{"learn":[4.184984466],"iteration":395,"passed_time":0.7654626813,"remaining_time":1.167523888},
{"learn":[4.182832144],"iteration":396,"passed_time":0.7668250411,"remaining_time":1.164724181},
{"learn":[4.179752812],"iteration":397,"passed_time":0.7683901587,"remaining_time":1.162238381},
{"learn":[4.17878934],"iteration":398,"passed_time":0.7698979123,"remaining_time":1.15967079},
{"learn":[4.174548229],"iteration":399,"passed_time":0.7715118049,"remaining_time":1.157267707},
{"learn":[4.168872556],"iteration":400,"passed_time":0.7729108371,"remaining_time":1.15454761},
{"learn":[4.163926494],"iteration":401,"passed_time":0.7744173748,"remaining_time":1.151994005},
{"learn":[4.159485076],"iteration":402,"passed_time":0.7760532686,"remaining_time":1.149637224},
{"learn":[4.155926102],"iteration":403,"passed_time":0.77754947,"remaining_time":1.147077931},
{"learn":[4.153540115],"iteration":404,"passed_time":0.7790015642,"remaining_time":1.144459088},
{"learn":[4.150983044],"iteration":405,"passed_time":0.7805115959,"remaining_time":1.141930759},
{"learn":[4.146539132],"iteration":406,"passed_time":0.78208421,"remaining_time":1.139498615},
{"learn":[4.144869174],"iteration":407,"passed_time":0.7835401272,"remaining_time":1.136901361},
{"learn":[4.142825962],"iteration":408,"passed_time":0.7851896581,"remaining_time":1.134589457},
{"learn":[4.142467378],"iteration":409,"passed_time":0.7866105645,"remaining_time":1.131951788},
{"learn":[4.141800768],"iteration":410,"passed_time":0.7880308634,"remaining_time":1.129319169},
{"learn":[4.140107084],"iteration":411,"passed_time":0.7896105992,"remaining_time":1.126919981},
{"learn":[4.136243196],"iteration":412,"passed_time":0.791061728,"remaining_time":1.124341972},
{"learn":[4.133618439],"iteration":413,"passed_time":0.7925521145,"remaining_time":1.121824974},
{"learn":[4.131053025],"iteration":414,"passed_time":0.7941191931,"remaining_time":1.119421031},
{"learn":[4.128379975],"iteration":415,"passed_time":0.7955337488,"remaining_time":1.116806994},
{"learn":[4.127068571],"iteration":416,"passed_time":0.7970249425,"remaining_time":1.114305855},
{"learn":[4.125969877],"iteration":417,"passed_time":0.7985519919,"remaining_time":1.111859472},
{"learn":[4.123893633],"iteration":418,"passed_time":0.8001631247,"remaining_time":1.10953407},
{"learn":[4.119643722],"iteration":419,"passed_time":0.8018021057,"remaining_time":1.107250527},
{"learn":[4.11465686],"iteration":420,"passed_time":0.8033255396,"remaining_time":1.104811134},
{"learn":[4.111565986],"iteration":421,"passed_time":0.8048506508,"remaining_time":1.102378379},
{"learn":[4.106322452],"iteration":422,"passed_time":0.8064461939,"remaining_time":1.10004599},
{"learn":[4.104222175],"iteration":423,"passed_time":0.8079171802,"remaining_time":1.097547867},
{"learn":[4.103008002],"iteration":424,"passed_time":0.8094648144,"remaining_time":1.095158278},
{"learn":[4.099176337],"iteration":425,"passed_time":0.8109440799,"remaining_time":1.092680521},
{"learn":[4.096525716],"iteration":426,"passed_time":0.8124990467,"remaining_time":1.090309025},
{"learn":[4.094967724],"iteration":427,"passed_time":0.8143544944,"remaining_time":1.088342922},
{"learn":[4.094683584],"iteration":428,"passed_time":0.8160249669,"remaining_time":1.086131133},
{"learn":[4.091096563],"iteration":429,"passed_time":0.8173919685,"remaining_time":1.083519586},
{"learn":[4.089178677],"iteration":430,"passed_time":0.8188304553,"remaining_time":1.081008188},
{"learn":[4.085335077],"iteration":431,"passed_time":0.8203663933,"remaining_time":1.078629888},
{"learn":[4.084852122],"iteration":432,"passed_time":0.8218940462,"remaining_time":1.076244629},
{"learn":[4.080322952],"iteration":433,"passed_time":0.8233786331,"remaining_time":1.073807158},
{"learn":[4.077449519],"iteration":434,"passed_time":0.8249332813,"remaining_time":1.071465067},
{"learn":[4.076568374],"iteration":435,"passed_time":0.8265613917,"remaining_time":1.069221617},
{"learn":[4.076071793],"iteration":436,"passed_time":0.828147491,"remaining_time":1.066926859},
{"learn":[4.075027644],"iteration":437,"passed_time":0.8295149543,"remaining_time":1.064354804},
{"learn":[4.07020837],"iteration":438,"passed_time":0.8309183337,"remaining_time":1.061834135},
{"learn":[4.06833694],"iteration":439,"passed_time":0.832378261,"remaining_time":1.059390514},
{"learn":[4.063936568],"iteration":440,"passed_time":0.8339272222,"remaining_time":1.057064211},
{"learn":[4.061734926],"iteration":441,"passed_time":0.8354176509,"remaining_time":1.054667532},
{"learn":[4.060815619],"iteration":442,"passed_time":0.8368895445,"remaining_time":1.052251639},
{"learn":[4.056407489],"iteration":443,"passed_time":0.8384523376,"remaining_time":1.049953828},
{"learn":[4.05238936],"iteration":444,"passed_time":0.8399381497,"remaining_time":1.04756331},
{"learn":[4.049685254],"iteration":445,"passed_time":0.841479497,"remaining_time":1.045245833},
{"learn":[4.045162016],"iteration":446,"passed_time":0.8431515964,"remaining_time":1.043093586},
{"learn":[4.042955482],"iteration":447,"passed_time":0.8448668995,"remaining_time":1.040996715},
{"learn":[4.041467663],"iteration":448,"passed_time":0.8464079037,"remaining_time":1.03868765},
{"learn":[4.038920476],"iteration":449,"passed_time":0.847902326,"remaining_time":1.036325065},
{"learn":[4.036694383],"iteration":450,"passed_time":0.8493862585,"remaining_time":1.033953561},
{"learn":[4.034999007],"iteration":451,"passed_time":0.8508582832,"remaining_time":1.031571547},
{"learn":[4.031928018],"iteration":452,"passed_time":0.8522810897,"remaining_time":1.029134119},
{"learn":[4.028718143],"iteration":453,"passed_time":0.8537691622,"remaining_time":1.026779653},
{"learn":[4.027401978],"iteration":454,"passed_time":0.8553317012,"remaining_time":1.024518192},
{"learn":[4.025930598],"iteration":455,"passed_time":0.8568715885,"remaining_time":1.022232772},
{"learn":[4.021074523],"iteration":456,"passed_time":0.858504739,"remaining_time":1.02006143},
{"learn":[4.020268486],"iteration":457,"passed_time":0.8598902884,"remaining_time":1.017599424},
{"learn":[4.017986361],"iteration":458,"passed_time":0.8612854784,"remaining_time":1.015153472},
{"learn":[4.014814804],"iteration":459,"passed_time":0.8629247732,"remaining_time":1.012998647},
{"learn":[4.009704796],"iteration":460,"passed_time":0.8643788677,"remaining_time":1.010629522},
{"learn":[4.008440457],"iteration":461,"passed_time":0.8657965911,"remaining_time":1.008222004},
{"learn":[4.004854849],"iteration":462,"passed_time":0.8671967391,"remaining_time":1.005798378},
{"learn":[4.000898028],"iteration":463,"passed_time":0.8687390062,"remaining_time":1.003543335},
{"learn":[3.996617985],"iteration":464,"passed_time":0.8701643359,"remaining_time":1.001156817},
{"learn":[3.995443319],"iteration":465,"passed_time":0.8717277839,"remaining_time":0.9989326966},
{"learn":[3.990771995],"iteration":466,"passed_time":0.873151111,"remaining_time":0.9965514822},
{"learn":[3.989249359],"iteration":467,"passed_time":0.8747184265,"remaining_time":0.9943380403},
{"learn":[3.986599538],"iteration":468,"passed_time":0.8761832649,"remaining_time":0.9920113298},
{"learn":[3.985628919],"iteration":469,"passed_time":0.8776283003,"remaining_time":0.9896659556},
{"learn":[3.985086112],"iteration":470,"passed_time":0.8791158385,"remaining_time":0.9873721414},
{"learn":[3.98466839],"iteration":471,"passed_time":0.8805571215,"remaining_time":0.9850300003},
{"learn":[3.984233894],"iteration":472,"passed_time":0.8819339376,"remaining_time":0.9826198417},
{"learn":[3.981855845],"iteration":473,"passed_time":0.8833842279,"remaining_time":0.9802955778},
{"learn":[3.978684264],"iteration":474,"passed_time":0.8848762945,"remaining_time":0.9780211676},
{"learn":[3.974361269],"iteration":475,"passed_time":0.8865478007,"remaining_time":0.9759475789},
{"learn":[3.972074049],"iteration":476,"passed_time":0.88805473,"remaining_time":0.973695228},
{"learn":[3.97191982],"iteration":477,"passed_time":0.8894419514,"remaining_time":0.9713152691},
{"learn":[3.969616848],"iteration":478,"passed_time":0.8909389611,"remaining_time":0.96905887},
{"learn":[3.968533527],"iteration":479,"passed_time":0.8922739829,"remaining_time":0.9666301482},
{"learn":[3.967568753],"iteration":480,"passed_time":0.8937678334,"remaining_time":0.9643773503},
{"learn":[3.966232553],"iteration":481,"passed_time":0.8952535421,"remaining_time":0.9621189519},
{"learn":[3.961522393],"iteration":482,"passed_time":0.896692341,"remaining_time":0.959813541},
{"learn":[3.955829553],"iteration":483,"passed_time":0.8981461686,"remaining_time":0.9575277335},
{"learn":[3.954248095],"iteration":484,"passed_time":0.8994695351,"remaining_time":0.955106826},
{"learn":[3.951922606],"iteration":485,"passed_time":0.9010502777,"remaining_time":0.9529626394},
{"learn":[3.94978202],"iteration":486,"passed_time":0.9026056337,"remaining_time":0.9507940248},
{"learn":[3.949518999],"iteration":487,"passed_time":0.904038825,"remaining_time":0.9484997508},
{"learn":[3.945431216],"iteration":488,"passed_time":0.9054283709,"remaining_time":0.9461633896},
{"learn":[3.943249086],"iteration":489,"passed_time":0.906941551,"remaining_time":0.9439595735},
{"learn":[3.941981548],"iteration":490,"passed_time":0.9084399306,"remaining_time":0.9417432274},
{"learn":[3.936600517],"iteration":491,"passed_time":0.9100543317,"remaining_time":0.9396495946},
{"learn":[3.934476885],"iteration":492,"passed_time":0.9116391966,"remaining_time":0.9375275308},
{"learn":[3.93045798],"iteration":493,"passed_time":0.9130764526,"remaining_time":0.9352564474},
{"learn":[3.925977375],"iteration":494,"passed_time":0.9146251101,"remaining_time":0.933102385},
{"learn":[3.92457993],"iteration":495,"passed_time":0.9161920628,"remaining_time":0.9309693541},
{"learn":[3.919849146],"iteration":496,"passed_time":0.917650664,"remaining_time":0.9287289416},
{"learn":[3.919681964],"iteration":497,"passed_time":0.9191344999,"remaining_time":0.9265171063},
{"learn":[3.917633027],"iteration":498,"passed_time":0.9206633591,"remaining_time":0.9243533926},
{"learn":[3.916616419],"iteration":499,"passed_time":0.9221114929,"remaining_time":0.9221114929},
{"learn":[3.912896166],"iteration":500,"passed_time":0.9236503153,"remaining_time":0.9199630885},
{"learn":[3.912769674],"iteration":501,"passed_time":0.9250125633,"remaining_time":0.9176419453},
{"learn":[3.909373788],"iteration":502,"passed_time":0.9264914641,"remaining_time":0.915439876},
{"learn":[3.906706036],"iteration":503,"passed_time":0.9279373599,"remaining_time":0.9132081955},
{"learn":[3.903895664],"iteration":504,"passed_time":0.9294353191,"remaining_time":0.9110306593},
{"learn":[3.902982967],"iteration":505,"passed_time":0.9312658843,"remaining_time":0.9091805274},
{"learn":[3.900905528],"iteration":506,"passed_time":0.9328667024,"remaining_time":0.9071070696},
{"learn":[3.897463465],"iteration":507,"passed_time":0.9343741647,"remaining_time":0.9049450572},
{"learn":[3.895918033],"iteration":508,"passed_time":0.935894756,"remaining_time":0.9027982813},
{"learn":[3.893921936],"iteration":509,"passed_time":0.9374111964,"remaining_time":0.900649973},
{"learn":[3.890237934],"iteration":510,"passed_time":0.9390649647,"remaining_time":0.8986355533},
{"learn":[3.887311613],"iteration":511,"passed_time":0.9404920515,"remaining_time":0.8964064866},
{"learn":[3.884869735],"iteration":512,"passed_time":0.9420364924,"remaining_time":0.8942919528},
{"learn":[3.882101231],"iteration":513,"passed_time":0.943639968,"remaining_time":0.8922354561},
{"learn":[3.88060368],"iteration":514,"passed_time":0.9453717894,"remaining_time":0.8903015881},
{"learn":[3.877726076],"iteration":515,"passed_time":0.9469206969,"remaining_time":0.8881969328},
{"learn":[3.874938145],"iteration":516,"passed_time":0.9484294709,"remaining_time":0.8860569332},
{"learn":[3.874340833],"iteration":517,"passed_time":0.9499839011,"remaining_time":0.8839618539},
{"learn":[3.873105224],"iteration":518,"passed_time":0.95152711,"remaining_time":0.8818584584},
{"learn":[3.869800236],"iteration":519,"passed_time":0.9531432625,"remaining_time":0.87982455},
{"learn":[3.867932518],"iteration":520,"passed_time":0.9546622896,"remaining_time":0.8777029495},
{"learn":[3.866666962],"iteration":521,"passed_time":0.95620569,"remaining_time":0.8756059767},
{"learn":[3.865527652],"iteration":522,"passed_time":0.9577412518,"remaining_time":0.8735039715},
{"learn":[3.861900081],"iteration":523,"passed_time":0.9592729921,"remaining_time":0.871400657},
{"learn":[3.858502887],"iteration":524,"passed_time":0.9609495905,"remaining_time":0.8694305819},
{"learn":[3.858335097],"iteration":525,"passed_time":0.9624738721,"remaining_time":0.8673243638},
{"learn":[3.855719306],"iteration":526,"passed_time":0.9640758689,"remaining_time":0.8652901062},
{"learn":[3.855137428],"iteration":527,"passed_time":0.9655794409,"remaining_time":0.8631695002},
{"learn":[3.851985706],"iteration":528,"passed_time":0.9671718568,"remaining_time":0.86113033},
{"learn":[3.851051809],"iteration":529,"passed_time":0.9686204258,"remaining_time":0.8589652833},
{"learn":[3.850679146],"iteration":530,"passed_time":0.9700794342,"remaining_time":0.8568121556},
{"learn":[3.848179484],"iteration":531,"passed_time":0.9715120941,"remaining_time":0.8546384587},
{"learn":[3.844551071],"iteration":532,"passed_time":0.9730946718,"remaining_time":0.8525988963},
{"learn":[3.841604794],"iteration":533,"passed_time":0.9746795359,"remaining_time":0.8505630407},
{"learn":[3.83969656],"iteration":534,"passed_time":0.9762199935,"remaining_time":0.8484902747},
{"learn":[3.836811463],"iteration":535,"passed_time":0.9777419394,"remaining_time":0.8464034699},
{"learn":[3.834182551],"iteration":536,"passed_time":0.9791227123,"remaining_time":0.8441970499},
{"learn":[3.828012842],"iteration":537,"passed_time":0.9805140901,"remaining_time":0.842002806},
{"learn":[3.826636176],"iteration":538,"passed_time":0.9819886293,"remaining_time":0.8398826681},
{"learn":[3.826189798],"iteration":539,"passed_time":0.9835124271,"remaining_time":0.8378068824},
{"learn":[3.824104738],"iteration":540,"passed_time":0.9849959087,"remaining_time":0.8356989318},
{"learn":[3.82300218],"iteration":541,"passed_time":0.9864409277,"remaining_time":0.8335607839},
{"learn":[3.817146402],"iteration":542,"passed_time":0.9880738686,"remaining_time":0.831583348},
{"learn":[3.814638044],"iteration":543,"passed_time":0.989520001,"remaining_time":0.829450589},
{"learn":[3.812979573],"iteration":544,"passed_time":0.9910298338,"remaining_time":0.827373531},
{"learn":[3.811938825],"iteration":545,"passed_time":0.9925887675,"remaining_time":0.8253393781},
{"learn":[3.811479418],"iteration":546,"passed_time":0.9940598953,"remaining_time":0.823234246},
{"learn":[3.80742981],"iteration":547,"passed_time":0.9955398328,"remaining_time":0.8211386942},
{"learn":[3.805097043],"iteration":548,"passed_time":0.9970801522,"remaining_time":0.8190949884},
{"learn":[3.801577232],"iteration":549,"passed_time":0.9986326282,"remaining_time":0.8170630594},
{"learn":[3.799762083],"iteration":550,"passed_time":0.9999731851,"remaining_time":0.8148601817},
{"learn":[3.796393455],"iteration":551,"passed_time":1.001376855,"remaining_time":0.8127116508},
{"learn":[3.793486459],"iteration":552,"passed_time":1.002993126,"remaining_time":0.8107376626},
{"learn":[3.792006091],"iteration":553,"passed_time":1.004498386,"remaining_time":0.8086755961},
{"learn":[3.78932128],"iteration":554,"passed_time":1.005905413,"remaining_time":0.8065367723},
{"learn":[3.787581812],"iteration":555,"passed_time":1.007373318,"remaining_time":0.8044491966},
{"learn":[3.785308865],"iteration":556,"passed_time":1.008865733,"remaining_time":0.8023833385},
{"learn":[3.78465475],"iteration":557,"passed_time":1.010210514,"remaining_time":0.8002025933},
{"learn":[3.780498869],"iteration":558,"passed_time":1.011584294,"remaining_time":0.798047717},
{"learn":[3.778734909],"iteration":559,"passed_time":1.013049332,"remaining_time":0.7959673326},
{"learn":[3.778652349],"iteration":560,"passed_time":1.014516726,"remaining_time":0.7938909854},
{"learn":[3.777928006],"iteration":561,"passed_time":1.017061498,"remaining_time":0.79265647},
{"learn":[3.776131406],"iteration":562,"passed_time":1.018562928,"remaining_time":0.7906074594},
{"learn":[3.772925617],"iteration":563,"passed_time":1.020101811,"remaining_time":0.7885893434},
{"learn":[3.7727745],"iteration":564,"passed_time":1.021693929,"remaining_time":0.7866139102},
{"learn":[3.771763073],"iteration":565,"passed_time":1.02340095,"remaining_time":0.7847279373},
{"learn":[3.768738162],"iteration":566,"passed_time":1.024987475,"remaining_time":0.7827505758},
{"learn":[3.767220794],"iteration":567,"passed_time":1.026521351,"remaining_time":0.7807345487},
{"learn":[3.766691102],"iteration":568,"passed_time":1.027947115,"remaining_time":0.7786383243},
{"learn":[3.766259335],"iteration":569,"passed_time":1.029520555,"remaining_time":0.7766558572},
{"learn":[3.76116362],"iteration":570,"passed_time":1.0309317,"remaining_time":0.7745528882},
{"learn":[3.758633056],"iteration":571,"passed_time":1.03238262,"remaining_time":0.7724821004},
{"learn":[3.754603809],"iteration":572,"passed_time":1.033814593,"remaining_time":0.7703993564},
{"learn":[3.754070549],"iteration":573,"passed_time":1.035278808,"remaining_time":0.7683428087},
{"learn":[3.750534319],"iteration":574,"passed_time":1.036705686,"remaining_time":0.7662607246},
{"learn":[3.746491516],"iteration":575,"passed_time":1.038113423,"remaining_time":0.7641668252},
{"learn":[3.744210544],"iteration":576,"passed_time":1.039582778,"remaining_time":0.7621204771},
{"learn":[3.742929991],"iteration":577,"passed_time":1.041023687,"remaining_time":0.7600553563},
{"learn":[3.740402992],"iteration":578,"passed_time":1.042514631,"remaining_time":0.7580287732},
{"learn":[3.739644243],"iteration":579,"passed_time":1.044187145,"remaining_time":0.7561355189},
{"learn":[3.737529404],"iteration":580,"passed_time":1.045941836,"remaining_time":0.7543022881},
{"learn":[3.737196923],"iteration":581,"passed_time":1.047396784,"remaining_time":0.7522540479},
{"learn":[3.733954464],"iteration":582,"passed_time":1.049157867,"remaining_time":0.7504268106},
{"learn":[3.731608623],"iteration":583,"passed_time":1.050771465,"remaining_time":0.748494742},
{"learn":[3.729843952],"iteration":584,"passed_time":1.052229635,"remaining_time":0.7464535015},
{"learn":[3.727223798],"iteration":585,"passed_time":1.053700981,"remaining_time":0.7444235598},
{"learn":[3.725351667],"iteration":586,"passed_time":1.055157079,"remaining_time":0.7423847931},
{"learn":[3.725026912],"iteration":587,"passed_time":1.056673602,"remaining_time":0.7403903468},
{"learn":[3.721974565],"iteration":588,"passed_time":1.058266212,"remaining_time":0.7384506163},
{"learn":[3.720269493],"iteration":589,"passed_time":1.059778466,"remaining_time":0.7364562224},
{"learn":[3.718907466],"iteration":590,"passed_time":1.061188559,"remaining_time":0.7343927589},
{"learn":[3.715602912],"iteration":591,"passed_time":1.062783867,"remaining_time":0.7324591519},
{"learn":[3.714463059],"iteration":592,"passed_time":1.064240585,"remaining_time":0.7304315651},
{"learn":[3.710802077],"iteration":593,"passed_time":1.065881437,"remaining_time":0.7285317567},
{"learn":[3.708032435],"iteration":594,"passed_time":1.067408941,"remaining_time":0.7265556654},
{"learn":[3.703788939],"iteration":595,"passed_time":1.068864334,"remaining_time":0.7245321993},
{"learn":[3.702500944],"iteration":596,"passed_time":1.070254478,"remaining_time":0.7224665905},
{"learn":[3.698196925],"iteration":597,"passed_time":1.071724701,"remaining_time":0.7204570733},
{"learn":[3.69658891],"iteration":598,"passed_time":1.073318804,"remaining_time":0.7185322879},
{"learn":[3.696124066],"iteration":599,"passed_time":1.074775005,"remaining_time":0.7165166701},
{"learn":[3.693537052],"iteration":600,"passed_time":1.076243486,"remaining_time":0.7145110663},
{"learn":[3.691343275],"iteration":601,"passed_time":1.077665645,"remaining_time":0.7124766227},
{"learn":[3.690973831],"iteration":602,"passed_time":1.079167379,"remaining_time":0.7104965992},
{"learn":[3.686151073],"iteration":603,"passed_time":1.080735693,"remaining_time":0.7085618119},
{"learn":[3.683921982],"iteration":604,"passed_time":1.08219116,"remaining_time":0.7065545593},
{"learn":[3.679975271],"iteration":605,"passed_time":1.083675438,"remaining_time":0.7045678587},
{"learn":[3.674047638],"iteration":606,"passed_time":1.08520162,"remaining_time":0.7026099448},
{"learn":[3.673151794],"iteration":607,"passed_time":1.086665982,"remaining_time":0.7006135936},
{"learn":[3.670953108],"iteration":608,"passed_time":1.088254911,"remaining_time":0.6986989661},
{"learn":[3.6703947],"iteration":609,"passed_time":1.089598883,"remaining_time":0.6966287938},
{"learn":[3.668433805],"iteration":610,"passed_time":1.091173856,"remaining_time":0.6947080687},
{"learn":[3.668304956],"iteration":611,"passed_time":1.092610154,"remaining_time":0.692700555},
{"learn":[3.667880012],"iteration":612,"passed_time":1.094023305,"remaining_time":0.6906802922},
{"learn":[3.667282264],"iteration":613,"passed_time":1.095533187,"remaining_time":0.6887228178},
{"learn":[3.664611483],"iteration":614,"passed_time":1.097047256,"remaining_time":0.6867694204},
{"learn":[3.662543394],"iteration":615,"passed_time":1.098637532,"remaining_time":0.6848649551},
{"learn":[3.659041959],"iteration":616,"passed_time":1.10009812,"remaining_time":0.6828810045},
{"learn":[3.656868545],"iteration":617,"passed_time":1.101596295,"remaining_time":0.6809219818},
{"learn":[3.654785614],"iteration":618,"passed_time":1.103114068,"remaining_time":0.6789765102},
{"learn":[3.654566096],"iteration":619,"passed_time":1.104658925,"remaining_time":0.6770490186},
{"learn":[3.651007045],"iteration":620,"passed_time":1.106198912,"remaining_time":0.675119787},
{"learn":[3.648921786],"iteration":621,"passed_time":1.107736295,"remaining_time":0.6731902245},
{"learn":[3.647655706],"iteration":622,"passed_time":1.10917454,"remaining_time":0.671201929},
{"learn":[3.647241144],"iteration":623,"passed_time":1.110584921,"remaining_time":0.6691986065},
{"learn":[3.644195689],"iteration":624,"passed_time":1.111985333,"remaining_time":0.6671911998},
{"learn":[3.642632246],"iteration":625,"passed_time":1.113611311,"remaining_time":0.6653204959},
{"learn":[3.642523322],"iteration":626,"passed_time":1.114751448,"remaining_time":0.6631615473},
{"learn":[3.641494659],"iteration":627,"passed_time":1.116163158,"remaining_time":0.6611667117},
{"learn":[3.63976496],"iteration":628,"passed_time":1.117703672,"remaining_time":0.6592497015},
{"learn":[3.637945652],"iteration":629,"passed_time":1.119311945,"remaining_time":0.657373682},
{"learn":[3.636233667],"iteration":630,"passed_time":1.120725109,"remaining_time":0.6553844139},
{"learn":[3.635304404],"iteration":631,"passed_time":1.122062731,"remaining_time":0.6533529828},
{"learn":[3.632234951],"iteration":632,"passed_time":1.123594387,"remaining_time":0.6514362401},
{"learn":[3.631630987],"iteration":633,"passed_time":1.125058683,"remaining_time":0.6494818262},
{"learn":[3.630301009],"iteration":634,"passed_time":1.126513481,"remaining_time":0.6475234969},
{"learn":[3.629077964],"iteration":635,"passed_time":1.127925718,"remaining_time":0.6455423921},
{"learn":[3.628004522],"iteration":636,"passed_time":1.129447685,"remaining_time":0.643625604},
{"learn":[3.625062876],"iteration":637,"passed_time":1.130965753,"remaining_time":0.6417078412},
{"learn":[3.624917986],"iteration":638,"passed_time":1.13253374,"remaining_time":0.6398195309},
{"learn":[3.622887087],"iteration":639,"passed_time":1.134007569,"remaining_time":0.6378792577},
{"learn":[3.621220865],"iteration":640,"passed_time":1.135649149,"remaining_time":0.636034391},
{"learn":[3.621143844],"iteration":641,"passed_time":1.137156266,"remaining_time":0.6341151764},
{"learn":[3.620822821],"iteration":642,"passed_time":1.138604836,"remaining_time":0.6321647381},
{"learn":[3.619202826],"iteration":643,"passed_time":1.140112891,"remaining_time":0.6302487412},
{"learn":[3.618204882],"iteration":644,"passed_time":1.141583833,"remaining_time":0.6283135824},
{"learn":[3.614259666],"iteration":645,"passed_time":1.143040451,"remaining_time":0.6263720118},
{"learn":[3.613415661],"iteration":646,"passed_time":1.144538556,"remaining_time":0.6244545754},
{"learn":[3.611096773],"iteration":647,"passed_time":1.146104833,"remaining_time":0.6225754647},
{"learn":[3.610820695],"iteration":648,"passed_time":1.14768668,"remaining_time":0.6207057392},
{"learn":[3.609290065],"iteration":649,"passed_time":1.149194887,"remaining_time":0.6187972467},
{"learn":[3.60897947],"iteration":650,"passed_time":1.150602962,"remaining_time":0.6168363039},
{"learn":[3.606570702],"iteration":651,"passed_time":1.152085506,"remaining_time":0.6149168039},
{"learn":[3.606292637],"iteration":652,"passed_time":1.153496599,"remaining_time":0.6129606735},
{"learn":[3.602753838],"iteration":653,"passed_time":1.154908574,"remaining_time":0.6110066768},
{"learn":[3.599755869],"iteration":654,"passed_time":1.156437501,"remaining_time":0.6091159354},
{"learn":[3.599509575],"iteration":655,"passed_time":1.157983815,"remaining_time":0.6072354152},
{"learn":[3.595337722],"iteration":656,"passed_time":1.159416891,"remaining_time":0.6052967939},
{"learn":[3.595168561],"iteration":657,"passed_time":1.161395768,"remaining_time":0.6036433933},
{"learn":[3.59290559],"iteration":658,"passed_time":1.163116938,"remaining_time":0.6018556536},
{"learn":[3.592015928],"iteration":659,"passed_time":1.164571736,"remaining_time":0.5999308943},
{"learn":[3.590680403],"iteration":660,"passed_time":1.166119506,"remaining_time":0.5980552386},
{"learn":[3.590361532],"iteration":661,"passed_time":1.167471899,"remaining_time":0.5960808185},
{"learn":[3.589069739],"iteration":662,"passed_time":1.169086567,"remaining_time":0.5942415886},
{"learn":[3.585010186],"iteration":663,"passed_time":1.170521473,"remaining_time":0.5923120704},
{"learn":[3.582997552],"iteration":664,"passed_time":1.172091351,"remaining_time":0.5904520337},
{"learn":[3.582119256],"iteration":665,"passed_time":1.173553255,"remaining_time":0.5885387194},
{"learn":[3.579019356],"iteration":666,"passed_time":1.175148168,"remaining_time":0.5866931635},
{"learn":[3.57719559],"iteration":667,"passed_time":1.176865059,"remaining_time":0.5849089814},
{"learn":[3.574050046],"iteration":668,"passed_time":1.178552255,"remaining_time":0.5831103085},
{"learn":[3.572204518],"iteration":669,"passed_time":1.180129934,"remaining_time":0.581258027},
{"learn":[3.569508025],"iteration":670,"passed_time":1.18165115,"remaining_time":0.5793788799},
{"learn":[3.566268704],"iteration":671,"passed_time":1.183161194,"remaining_time":0.5774953448},
{"learn":[3.562564052],"iteration":672,"passed_time":1.18469544,"remaining_time":0.5756246788},
{"learn":[3.561173586],"iteration":673,"passed_time":1.186267781,"remaining_time":0.5737734369},
{"learn":[3.559551904],"iteration":674,"passed_time":1.187754924,"remaining_time":0.5718820003},
{"learn":[3.558593054],"iteration":675,"passed_time":1.189316514,"remaining_time":0.5700274418},
{"learn":[3.555647008],"iteration":676,"passed_time":1.190928228,"remaining_time":0.5681976629},
{"learn":[3.553100059],"iteration":677,"passed_time":1.192565104,"remaining_time":0.5663804773},
{"learn":[3.55085578],"iteration":678,"passed_time":1.194044902,"remaining_time":0.5644895635},
{"learn":[3.550737965],"iteration":679,"passed_time":1.195397301,"remaining_time":0.5625399064},
{"learn":[3.549408772],"iteration":680,"passed_time":1.196958502,"remaining_time":0.5606898124},
{"learn":[3.547390589],"iteration":681,"passed_time":1.198462767,"remaining_time":0.5588140176},
{"learn":[3.54723575],"iteration":682,"passed_time":1.199868826,"remaining_time":0.5568937303},
{"learn":[3.543988891],"iteration":683,"passed_time":1.201277368,"remaining_time":0.5549760938},
{"learn":[3.543868508],"iteration":684,"passed_time":1.202704833,"remaining_time":0.5530686459},
{"learn":[3.542752124],"iteration":685,"passed_time":1.204347654,"remaining_time":0.5512611712},
{"learn":[3.541334315],"iteration":686,"passed_time":1.205795005,"remaining_time":0.5493651189},
{"learn":[3.540208266],"iteration":687,"passed_time":1.207245163,"remaining_time":0.5474716435},
{"learn":[3.537730983],"iteration":688,"passed_time":1.208737356,"remaining_time":0.5455984292},
{"learn":[3.53419867],"iteration":689,"passed_time":1.210318773,"remaining_time":0.5437664051},
{"learn":[3.532628335],"iteration":690,"passed_time":1.211747062,"remaining_time":0.5418666314},
{"learn":[3.532204987],"iteration":691,"passed_time":1.213198201,"remaining_time":0.5399783901},
{"learn":[3.530618147],"iteration":692,"passed_time":1.214587671,"remaining_time":0.5380640909},
{"learn":[3.528909306],"iteration":693,"passed_time":1.216067643,"remaining_time":0.5361912084},
{"learn":[3.526700678],"iteration":694,"passed_time":1.21754249,"remaining_time":0.5343172078},
{"learn":[3.526439574],"iteration":695,"passed_time":1.218983229,"remaining_time":0.5324294564},
{"learn":[3.525784216],"iteration":696,"passed_time":1.220492383,"remaining_time":0.5305727291},
{"learn":[3.524112693],"iteration":697,"passed_time":1.222069127,"remaining_time":0.5287462412},
{"learn":[3.522813541],"iteration":698,"passed_time":1.223533059,"remaining_time":0.5268718895},
{"learn":[3.519148203],"iteration":699,"passed_time":1.224930064,"remaining_time":0.5249700274},
{"learn":[3.517236747],"iteration":700,"passed_time":1.226569547,"remaining_time":0.5231730308},
{"learn":[3.515603888],"iteration":701,"passed_time":1.228117562,"remaining_time":0.5213376546},
{"learn":[3.51263524],"iteration":702,"passed_time":1.229620748,"remaining_time":0.5194841566},
{"learn":[3.51123442],"iteration":703,"passed_time":1.231074702,"remaining_time":0.5176109541},
{"learn":[3.50828027],"iteration":704,"passed_time":1.23258323,"remaining_time":0.5157617769},
{"learn":[3.508265537],"iteration":705,"passed_time":1.233538238,"remaining_time":0.5136830622},
{"learn":[3.506774876],"iteration":706,"passed_time":1.235175116,"remaining_time":0.5118901117},
{"learn":[3.50552068],"iteration":707,"passed_time":1.236650113,"remaining_time":0.5100308377},
{"learn":[3.501973993],"iteration":708,"passed_time":1.238164509,"remaining_time":0.5081888184},
{"learn":[3.498880354],"iteration":709,"passed_time":1.239676421,"remaining_time":0.5063467073},
{"learn":[3.497370959],"iteration":710,"passed_time":1.241102389,"remaining_time":0.5044705912},
{"learn":[3.496050455],"iteration":711,"passed_time":1.242542127,"remaining_time":0.5026013099},
{"learn":[3.495630067],"iteration":712,"passed_time":1.243982033,"remaining_time":0.5007333008},
{"learn":[3.49550669],"iteration":713,"passed_time":1.245337233,"remaining_time":0.4988325613},
{"learn":[3.493652375],"iteration":714,"passed_time":1.2468879,"remaining_time":0.497011261},
{"learn":[3.491915684],"iteration":715,"passed_time":1.248402838,"remaining_time":0.4951765448},
{"learn":[3.490303956],"iteration":716,"passed_time":1.249903667,"remaining_time":0.4933371517},
{"learn":[3.488363853],"iteration":717,"passed_time":1.251564429,"remaining_time":0.4915615168},
{"learn":[3.485483936],"iteration":718,"passed_time":1.25296069,"remaining_time":0.4896828286},
{"learn":[3.483763466],"iteration":719,"passed_time":1.25449043,"remaining_time":0.4878573894},
{"learn":[3.481642352],"iteration":720,"passed_time":1.255938289,"remaining_time":0.4860010853},
{"learn":[3.479826119],"iteration":721,"passed_time":1.257429783,"remaining_time":0.4841627142},
{"learn":[3.478588728],"iteration":722,"passed_time":1.258937731,"remaining_time":0.4823316063},
{"learn":[3.475390887],"iteration":723,"passed_time":1.260397196,"remaining_time":0.4804829091},
{"learn":[3.472636852],"iteration":724,"passed_time":1.26187235,"remaining_time":0.4786412363},
{"learn":[3.47061883],"iteration":725,"passed_time":1.263447081,"remaining_time":0.4768381544},
{"learn":[3.46953149],"iteration":726,"passed_time":1.26486833,"remaining_time":0.4749780662},
{"learn":[3.467217162],"iteration":727,"passed_time":1.266421833,"remaining_time":0.4731685971},
{"learn":[3.465686216],"iteration":728,"passed_time":1.267828578,"remaining_time":0.4713052739},
{"learn":[3.462631216],"iteration":729,"passed_time":1.269223891,"remaining_time":0.4694389734},
{"learn":[3.461451053],"iteration":730,"passed_time":1.270616803,"remaining_time":0.467573078},
{"learn":[3.458950469],"iteration":731,"passed_time":1.272085331,"remaining_time":0.4657361594},
{"learn":[3.458072145],"iteration":732,"passed_time":1.273516617,"remaining_time":0.4638866804},
{"learn":[3.454364268],"iteration":733,"passed_time":1.274990706,"remaining_time":0.4620538525},
{"learn":[3.453243406],"iteration":734,"passed_time":1.27665065,"remaining_time":0.46028901},
{"learn":[3.453017963],"iteration":735,"passed_time":1.278423058,"remaining_time":0.4585647926},
{"learn":[3.45201581],"iteration":736,"passed_time":1.279962361,"remaining_time":0.4567572603},
{"learn":[3.449510107],"iteration":737,"passed_time":1.281442236,"remaining_time":0.4549293575},
{"learn":[3.447189189],"iteration":738,"passed_time":1.282929037,"remaining_time":0.4531048427},
{"learn":[3.446423605],"iteration":739,"passed_time":1.284399723,"remaining_time":0.4512755785},
{"learn":[3.445531987],"iteration":740,"passed_time":1.2857871,"remaining_time":0.449418163},
{"learn":[3.445328199],"iteration":741,"passed_time":1.287325475,"remaining_time":0.4476145183},
{"learn":[3.443327544],"iteration":742,"passed_time":1.288831361,"remaining_time":0.4458003496},
{"learn":[3.441475798],"iteration":743,"passed_time":1.29041595,"remaining_time":0.4440140902},
{"learn":[3.439046501],"iteration":744,"passed_time":1.292083233,"remaining_time":0.442256677},
{"learn":[3.435899469],"iteration":745,"passed_time":1.293529303,"remaining_time":0.4404241864},
{"learn":[3.433988352],"iteration":746,"passed_time":1.294985249,"remaining_time":0.438596075},
{"learn":[3.433413263],"iteration":747,"passed_time":1.296483148,"remaining_time":0.4367830927},
{"learn":[3.429944699],"iteration":748,"passed_time":1.298062503,"remaining_time":0.4349982487},
{"learn":[3.429291634],"iteration":749,"passed_time":1.29950326,"remaining_time":0.4331677532},
{"learn":[3.429175603],"iteration":750,"passed_time":1.300921744,"remaining_time":0.4313309112},
{"learn":[3.428780323],"iteration":751,"passed_time":1.302515082,"remaining_time":0.4295528462},
{"learn":[3.423893341],"iteration":752,"passed_time":1.304016647,"remaining_time":0.4277451684},
{"learn":[3.421024316],"iteration":753,"passed_time":1.305594895,"remaining_time":0.4259633213},
{"learn":[3.420969872],"iteration":754,"passed_time":1.307102234,"remaining_time":0.4241590031},
{"learn":[3.419544785],"iteration":755,"passed_time":1.308535876,"remaining_time":0.4223316849},
{"learn":[3.417057977],"iteration":756,"passed_time":1.310082366,"remaining_time":0.4205416313},
{"learn":[3.415160245],"iteration":757,"passed_time":1.311565584,"remaining_time":0.4187320202},
{"learn":[3.412854597],"iteration":758,"passed_time":1.313016401,"remaining_time":0.4169129811},
{"learn":[3.410926347],"iteration":759,"passed_time":1.314449125,"remaining_time":0.4150891973},
{"learn":[3.408963843],"iteration":760,"passed_time":1.315882509,"remaining_time":0.4132666488},
{"learn":[3.407629634],"iteration":761,"passed_time":1.317467235,"remaining_time":0.411492391},
{"learn":[3.404384724],"iteration":762,"passed_time":1.319030847,"remaining_time":0.4097120718},
{"learn":[3.403041656],"iteration":763,"passed_time":1.320522107,"remaining_time":0.4079099701},
{"learn":[3.401101731],"iteration":764,"passed_time":1.322032521,"remaining_time":0.4061145654},
{"learn":[3.400890668],"iteration":765,"passed_time":1.3235653,"remaining_time":0.4043267365},
{"learn":[3.399289941],"iteration":766,"passed_time":1.325075842,"remaining_time":0.4025328177},
{"learn":[3.399202366],"iteration":767,"passed_time":1.326441436,"remaining_time":0.4006958503},
{"learn":[3.397447845],"iteration":768,"passed_time":1.3280382,"remaining_time":0.3989295504},
{"learn":[3.394655341],"iteration":769,"passed_time":1.329471646,"remaining_time":0.3971149072},
{"learn":[3.393228229],"iteration":770,"passed_time":1.331005535,"remaining_time":0.3953310864},
{"learn":[3.389691197],"iteration":771,"passed_time":1.332659076,"remaining_time":0.3935832503},
{"learn":[3.389626772],"iteration":772,"passed_time":1.334252082,"remaining_time":0.3918178818},
{"learn":[3.388480222],"iteration":773,"passed_time":1.335739273,"remaining_time":0.3900220617},
{"learn":[3.388215066],"iteration":774,"passed_time":1.337191119,"remaining_time":0.3882167766},
{"learn":[3.386324358],"iteration":775,"passed_time":1.338659478,"remaining_time":0.3864171691},
{"learn":[3.383913061],"iteration":776,"passed_time":1.340122922,"remaining_time":0.3846170033},
{"learn":[3.382839768],"iteration":777,"passed_time":1.341608475,"remaining_time":0.3828240122},
{"learn":[3.381961844],"iteration":778,"passed_time":1.343042201,"remaining_time":0.3810171072},
{"learn":[3.381521703],"iteration":779,"passed_time":1.344674216,"remaining_time":0.3792670866},
{"learn":[3.380918963],"iteration":780,"passed_time":1.346076713,"remaining_time":0.3774530092},
{"learn":[3.377139006],"iteration":781,"passed_time":1.347639434,"remaining_time":0.3756846504},
{"learn":[3.376004372],"iteration":782,"passed_time":1.349294544,"remaining_time":0.3739424214},
{"learn":[3.373826468],"iteration":783,"passed_time":1.350729341,"remaining_time":0.3721397163},
{"learn":[3.373546786],"iteration":784,"passed_time":1.352074611,"remaining_time":0.3703134284},
{"learn":[3.372109181],"iteration":785,"passed_time":1.353544949,"remaining_time":0.3685224161},
{"learn":[3.370764924],"iteration":786,"passed_time":1.355018768,"remaining_time":0.3667331609},
{"learn":[3.367833107],"iteration":787,"passed_time":1.356614096,"remaining_time":0.3649773963},
{"learn":[3.36450404],"iteration":788,"passed_time":1.358094398,"remaining_time":0.3631912775},
{"learn":[3.361794558],"iteration":789,"passed_time":1.359556728,"remaining_time":0.3614011554},
{"learn":[3.356880529],"iteration":790,"passed_time":1.361026547,"remaining_time":0.3596138412},
{"learn":[3.353843509],"iteration":791,"passed_time":1.362505204,"remaining_time":0.3578296495},
{"learn":[3.353640253],"iteration":792,"passed_time":1.364096234,"remaining_time":0.3560755617},
{"learn":[3.353055088],"iteration":793,"passed_time":1.365613873,"remaining_time":0.3543028436},
{"learn":[3.351415617],"iteration":794,"passed_time":1.367115419,"remaining_time":0.3525266175},
{"learn":[3.349169061],"iteration":795,"passed_time":1.368584744,"remaining_time":0.3507428238},
{"learn":[3.346211014],"iteration":796,"passed_time":1.370038591,"remaining_time":0.3489558769},
{"learn":[3.344560452],"iteration":797,"passed_time":1.371537667,"remaining_time":0.3471812139},
{"learn":[3.344445461],"iteration":798,"passed_time":1.372991895,"remaining_time":0.3453959586},
{"learn":[3.342608898],"iteration":799,"passed_time":1.374399014,"remaining_time":0.3435997535},
{"learn":[3.339572899],"iteration":800,"passed_time":1.375924886,"remaining_time":0.3418340229},
{"learn":[3.339309302],"iteration":801,"passed_time":1.377550476,"remaining_time":0.340093509},
{"learn":[3.33698088],"iteration":802,"passed_time":1.379148413,"remaining_time":0.3383464973},
{"learn":[3.334746342],"iteration":803,"passed_time":1.380628495,"remaining_time":0.3365711258},
{"learn":[3.332048511],"iteration":804,"passed_time":1.382095858,"remaining_time":0.3347934065},
{"learn":[3.331932544],"iteration":805,"passed_time":1.38346996,"remaining_time":0.3329940102},
{"learn":[3.330541133],"iteration":806,"passed_time":1.385004755,"remaining_time":0.3312340987},
{"learn":[3.329124989],"iteration":807,"passed_time":1.386544612,"remaining_time":0.3294759473},
{"learn":[3.32583918],"iteration":808,"passed_time":1.38794771,"remaining_time":0.3276860477},
{"learn":[3.325287299],"iteration":809,"passed_time":1.389432581,"remaining_time":0.3259162845},
{"learn":[3.322745162],"iteration":810,"passed_time":1.390900446,"remaining_time":0.3241432605},
{"learn":[3.319733662],"iteration":811,"passed_time":1.392266168,"remaining_time":0.3223473394},
{"learn":[3.318080007],"iteration":812,"passed_time":1.394495956,"remaining_time":0.3207512224},
{"learn":[3.317179538],"iteration":813,"passed_time":1.395934918,"remaining_time":0.3189728436},
{"learn":[3.315685949],"iteration":814,"passed_time":1.397434431,"remaining_time":0.3172090425},
{"learn":[3.314944576],"iteration":815,"passed_time":1.398999319,"remaining_time":0.3154606308},
{"learn":[3.312369052],"iteration":816,"passed_time":1.400574813,"remaining_time":0.3137150438},
{"learn":[3.312321621],"iteration":817,"passed_time":1.401737711,"remaining_time":0.3118780727},
{"learn":[3.309465776],"iteration":818,"passed_time":1.40311837,"remaining_time":0.3100908729},
{"learn":[3.308307377],"iteration":819,"passed_time":1.404518035,"remaining_time":0.3083088369},
{"learn":[3.308076804],"iteration":820,"passed_time":1.406007577,"remaining_time":0.3065473279},
{"learn":[3.305643326],"iteration":821,"passed_time":1.407654715,"remaining_time":0.3048206074},
{"learn":[3.304154814],"iteration":822,"passed_time":1.409320777,"remaining_time":0.30309815},
{"learn":[3.303076321],"iteration":823,"passed_time":1.410852657,"remaining_time":0.3013471694},
{"learn":[3.301746372],"iteration":824,"passed_time":1.412579775,"remaining_time":0.299638134},
{"learn":[3.301345455],"iteration":825,"passed_time":1.414140346,"remaining_time":0.2978939712},
{"learn":[3.299181039],"iteration":826,"passed_time":1.415664844,"remaining_time":0.2961427061},
{"learn":[3.297989357],"iteration":827,"passed_time":1.41753892,"remaining_time":0.2944646065},
{"learn":[3.294775182],"iteration":828,"passed_time":1.419065945,"remaining_time":0.2927144471},
{"learn":[3.293840636],"iteration":829,"passed_time":1.420574351,"remaining_time":0.2909610118},
{"learn":[3.289279397],"iteration":830,"passed_time":1.4221873,"remaining_time":0.2892294268},
{"learn":[3.286204979],"iteration":831,"passed_time":1.423911864,"remaining_time":0.2875206648},
{"learn":[3.284833593],"iteration":832,"passed_time":1.425402359,"remaining_time":0.2857649387},
{"learn":[3.283519914],"iteration":833,"passed_time":1.426903645,"remaining_time":0.2840119964},
{"learn":[3.282853026],"iteration":834,"passed_time":1.428390906,"remaining_time":0.2822568856},
{"learn":[3.281944673],"iteration":835,"passed_time":1.430003178,"remaining_time":0.2805269392},
{"learn":[3.279764865],"iteration":836,"passed_time":1.431492089,"remaining_time":0.2787732503},
{"learn":[3.277468839],"iteration":837,"passed_time":1.433081268,"remaining_time":0.2770395769},
{"learn":[3.277124974],"iteration":838,"passed_time":1.43461581,"remaining_time":0.2752957633},
{"learn":[3.275636037],"iteration":839,"passed_time":1.43617815,"remaining_time":0.2735577428},
{"learn":[3.274413635],"iteration":840,"passed_time":1.437666642,"remaining_time":0.2718061784},
{"learn":[3.272636087],"iteration":841,"passed_time":1.439267981,"remaining_time":0.2700764145},
{"learn":[3.269644466],"iteration":842,"passed_time":1.440727684,"remaining_time":0.268320577},
{"learn":[3.26852083],"iteration":843,"passed_time":1.442204012,"remaining_time":0.2665685141},
{"learn":[3.267820927],"iteration":844,"passed_time":1.443664567,"remaining_time":0.2648142106},
{"learn":[3.267331099],"iteration":845,"passed_time":1.4451911,"remaining_time":0.2630726115},
{"learn":[3.267231014],"iteration":846,"passed_time":1.446748148,"remaining_time":0.2613370326},
{"learn":[3.267158695],"iteration":847,"passed_time":1.448109209,"remaining_time":0.2595667451},
{"learn":[3.264718705],"iteration":848,"passed_time":1.449636752,"remaining_time":0.2578270312},
{"learn":[3.261678512],"iteration":849,"passed_time":1.451135379,"remaining_time":0.256082714},
{"learn":[3.261368381],"iteration":850,"passed_time":1.452520299,"remaining_time":0.2543190653},
{"learn":[3.260128799],"iteration":851,"passed_time":1.454045645,"remaining_time":0.2525806988},
{"learn":[3.258972952],"iteration":852,"passed_time":1.455493994,"remaining_time":0.2508295629},
{"learn":[3.258724846],"iteration":853,"passed_time":1.456941379,"remaining_time":0.2490789711},
{"learn":[3.25686724],"iteration":854,"passed_time":1.458431908,"remaining_time":0.2473364055},
{"learn":[3.255750259],"iteration":855,"passed_time":1.459795925,"remaining_time":0.2455731463},
{"learn":[3.254915866],"iteration":856,"passed_time":1.461299404,"remaining_time":0.2438340895},
{"learn":[3.254348625],"iteration":857,"passed_time":1.462759816,"remaining_time":0.2420884544},
{"learn":[3.253408514],"iteration":858,"passed_time":1.464221025,"remaining_time":0.240343614},
{"learn":[3.253291714],"iteration":859,"passed_time":1.465669748,"remaining_time":0.2385974009},
{"learn":[3.250186342],"iteration":860,"passed_time":1.467254812,"remaining_time":0.2368738895},
{"learn":[3.249141318],"iteration":861,"passed_time":1.468808144,"remaining_time":0.2351456193},
{"learn":[3.246300388],"iteration":862,"passed_time":1.470184518,"remaining_time":0.2333896628},
{"learn":[3.245205135],"iteration":863,"passed_time":1.471636115,"remaining_time":0.2316464255},
{"learn":[3.244403535],"iteration":864,"passed_time":1.47313327,"remaining_time":0.2299109727},
{"learn":[3.244211781],"iteration":865,"passed_time":1.474574709,"remaining_time":0.2281674491},
{"learn":[3.242286347],"iteration":866,"passed_time":1.476090775,"remaining_time":0.2264360705},
{"learn":[3.239606746],"iteration":867,"passed_time":1.477533087,"remaining_time":0.2246939718},
{"learn":[3.236773361],"iteration":868,"passed_time":1.479008705,"remaining_time":0.2229575838},
{"learn":[3.234552446],"iteration":869,"passed_time":1.480475047,"remaining_time":0.2212204093},
{"learn":[3.233724647],"iteration":870,"passed_time":1.482059745,"remaining_time":0.2195013859},
{"learn":[3.230851485],"iteration":871,"passed_time":1.483606666,"remaining_time":0.2177771254},
{"learn":[3.227728941],"iteration":872,"passed_time":1.485058079,"remaining_time":0.216039377},
{"learn":[3.225787575],"iteration":873,"passed_time":1.486690789,"remaining_time":0.2143284203},
{"learn":[3.222797487],"iteration":874,"passed_time":1.488131279,"remaining_time":0.2125901828},
{"learn":[3.22137014],"iteration":875,"passed_time":1.489573646,"remaining_time":0.2108528905},
{"learn":[3.219701963],"iteration":876,"passed_time":1.491118293,"remaining_time":0.2091306158},
{"learn":[3.21783327],"iteration":877,"passed_time":1.492626207,"remaining_time":0.2074036415},
{"learn":[3.217713355],"iteration":878,"passed_time":1.493990622,"remaining_time":0.2056574122},
{"learn":[3.217666091],"iteration":879,"passed_time":1.495478865,"remaining_time":0.2039289362},
{"learn":[3.214962005],"iteration":880,"passed_time":1.497013121,"remaining_time":0.2022072207},
{"learn":[3.214081828],"iteration":881,"passed_time":1.498470506,"remaining_time":0.2004756459},
{"learn":[3.213358337],"iteration":882,"passed_time":1.500173284,"remaining_time":0.1987772076},
{"learn":[3.210850401],"iteration":883,"passed_time":1.501698231,"remaining_time":0.197055424},
{"learn":[3.207810328],"iteration":884,"passed_time":1.503434969,"remaining_time":0.1953616062},
{"learn":[3.204935073],"iteration":885,"passed_time":1.505230799,"remaining_time":0.1936752947},
{"learn":[3.20280198],"iteration":886,"passed_time":1.506986312,"remaining_time":0.1919836},
{"learn":[3.200663495],"iteration":887,"passed_time":1.508578656,"remaining_time":0.1902711818},
{"learn":[3.197301669],"iteration":888,"passed_time":1.510115694,"remaining_time":0.1885521282},
{"learn":[3.195666943],"iteration":889,"passed_time":1.511741997,"remaining_time":0.1868445165},
{"learn":[3.193886506],"iteration":890,"passed_time":1.5133377,"remaining_time":0.1851333437},
{"learn":[3.190601248],"iteration":891,"passed_time":1.515083051,"remaining_time":0.1834405487},
{"learn":[3.188983797],"iteration":892,"passed_time":1.516794611,"remaining_time":0.1817435872},
{"learn":[3.187365749],"iteration":893,"passed_time":1.518763884,"remaining_time":0.1800771495},
{"learn":[3.186160771],"iteration":894,"passed_time":1.520454286,"remaining_time":0.1783773185},
{"learn":[3.185358981],"iteration":895,"passed_time":1.52212242,"remaining_time":0.1766749238},
{"learn":[3.183832164],"iteration":896,"passed_time":1.523881194,"remaining_time":0.1749830133},
{"learn":[3.183106966],"iteration":897,"passed_time":1.525576968,"remaining_time":0.1732837981},
{"learn":[3.182838152],"iteration":898,"passed_time":1.52734879,"remaining_time":0.1715931344},
{"learn":[3.180835453],"iteration":899,"passed_time":1.529070531,"remaining_time":0.1698967257},
{"learn":[3.179957348],"iteration":900,"passed_time":1.530740302,"remaining_time":0.1681945504},
{"learn":[3.179752966],"iteration":901,"passed_time":1.532230079,"remaining_time":0.1664728911},
{"learn":[3.178851983],"iteration":902,"passed_time":1.533864635,"remaining_time":0.1647672975},
{"learn":[3.176748586],"iteration":903,"passed_time":1.535766785,"remaining_time":0.1630902781},
{"learn":[3.172960988],"iteration":904,"passed_time":1.537407965,"remaining_time":0.1613853664},
{"learn":[3.172794225],"iteration":905,"passed_time":1.539281711,"remaining_time":0.159704725},
{"learn":[3.169996507],"iteration":906,"passed_time":1.541215418,"remaining_time":0.1580298058},
{"learn":[3.16813015],"iteration":907,"passed_time":1.543079103,"remaining_time":0.1563472219},
{"learn":[3.166920871],"iteration":908,"passed_time":1.544705964,"remaining_time":0.1546405311},
{"learn":[3.16531606],"iteration":909,"passed_time":1.54632936,"remaining_time":0.152933673},
{"learn":[3.162035247],"iteration":910,"passed_time":1.548066851,"remaining_time":0.1512381446},
{"learn":[3.16189467],"iteration":911,"passed_time":1.549588502,"remaining_time":0.1495216976},
{"learn":[3.161008416],"iteration":912,"passed_time":1.551347011,"remaining_time":0.1478282475},
{"learn":[3.160560787],"iteration":913,"passed_time":1.552879277,"remaining_time":0.1461133674},
{"learn":[3.160416261],"iteration":914,"passed_time":1.554520088,"remaining_time":0.1444089699},
{"learn":[3.15844291],"iteration":915,"passed_time":1.556119741,"remaining_time":0.142700937},
{"learn":[3.155040501],"iteration":916,"passed_time":1.557738022,"remaining_time":0.1409948264},
{"learn":[3.154937548],"iteration":917,"passed_time":1.559186027,"remaining_time":0.1392736974},
{"learn":[3.153721161],"iteration":918,"passed_time":1.560849996,"remaining_time":0.1375721977},
{"learn":[3.153170511],"iteration":919,"passed_time":1.562376901,"remaining_time":0.1358588609},
{"learn":[3.153113601],"iteration":920,"passed_time":1.564021942,"remaining_time":0.1341560623},
{"learn":[3.150607379],"iteration":921,"passed_time":1.565379967,"remaining_time":0.1324291079},
{"learn":[3.148408359],"iteration":922,"passed_time":1.567048279,"remaining_time":0.130728838},
{"learn":[3.147495728],"iteration":923,"passed_time":1.568528689,"remaining_time":0.1290131822},
{"learn":[3.146946235],"iteration":924,"passed_time":1.569921417,"remaining_time":0.1272909257},
{"learn":[3.14472738],"iteration":925,"passed_time":1.571531841,"remaining_time":0.1255867778},
{"learn":[3.144469477],"iteration":926,"passed_time":1.573141984,"remaining_time":0.12388281},
{"learn":[3.142975516],"iteration":927,"passed_time":1.574754426,"remaining_time":0.1221792227},
{"learn":[3.14079113],"iteration":928,"passed_time":1.576176919,"remaining_time":0.1204613146},
{"learn":[3.138173032],"iteration":929,"passed_time":1.577688236,"remaining_time":0.1187507274},
{"learn":[3.136352813],"iteration":930,"passed_time":1.5791203,"remaining_time":0.1170346946},
{"learn":[3.133735004],"iteration":931,"passed_time":1.5806451,"remaining_time":0.1153260373},
{"learn":[3.1319496],"iteration":932,"passed_time":1.582133332,"remaining_time":0.1136151482},
{"learn":[3.129865343],"iteration":933,"passed_time":1.583831375,"remaining_time":0.1119195618},
{"learn":[3.129830206],"iteration":934,"passed_time":1.58508416,"remaining_time":0.1101930165},
{"learn":[3.126676562],"iteration":935,"passed_time":1.586713313,"remaining_time":0.108493218},
{"learn":[3.12645665],"iteration":936,"passed_time":1.588342228,"remaining_time":0.1067935543},
{"learn":[3.126378007],"iteration":937,"passed_time":1.589764599,"remaining_time":0.1050803893},
{"learn":[3.124621914],"iteration":938,"passed_time":1.591294313,"remaining_time":0.1033748169},
{"learn":[3.123379018],"iteration":939,"passed_time":1.592744934,"remaining_time":0.1016645703},
{"learn":[3.123332451],"iteration":940,"passed_time":1.594192207,"remaining_time":0.09995466545},
{"learn":[3.122432444],"iteration":941,"passed_time":1.595640885,"remaining_time":0.09824540479},
{"learn":[3.121889006],"iteration":942,"passed_time":1.597120402,"remaining_time":0.0965385609},
{"learn":[3.121070914],"iteration":943,"passed_time":1.598603156,"remaining_time":0.09483239061},
{"learn":[3.118444705],"iteration":944,"passed_time":1.600032467,"remaining_time":0.09312358276},
{"learn":[3.116820458],"iteration":945,"passed_time":1.601540094,"remaining_time":0.09141983626},
{"learn":[3.114971041],"iteration":946,"passed_time":1.603094539,"remaining_time":0.08971912417},
{"learn":[3.114685138],"iteration":947,"passed_time":1.604580731,"remaining_time":0.08801497681},
{"learn":[3.113399363],"iteration":948,"passed_time":1.606150183,"remaining_time":0.08631576324},
{"learn":[3.110575399],"iteration":949,"passed_time":1.607657195,"remaining_time":0.08461353658},
{"learn":[3.110466553],"iteration":950,"passed_time":1.609245822,"remaining_time":0.08291592563},
{"learn":[3.108691641],"iteration":951,"passed_time":1.610892779,"remaining_time":0.08122148466},
{"learn":[3.107898017],"iteration":952,"passed_time":1.612264765,"remaining_time":0.07951358231},
{"learn":[3.105551729],"iteration":953,"passed_time":1.613767691,"remaining_time":0.07781269789},
{"learn":[3.104824945],"iteration":954,"passed_time":1.61532279,"remaining_time":0.07611468642},
{"learn":[3.103186704],"iteration":955,"passed_time":1.616885015,"remaining_time":0.07441730194},
{"learn":[3.102330655],"iteration":956,"passed_time":1.618295838,"remaining_time":0.07271339712},
{"learn":[3.102291298],"iteration":957,"passed_time":1.619830346,"remaining_time":0.07101552665},
{"learn":[3.100363529],"iteration":958,"passed_time":1.621247401,"remaining_time":0.06931297543},
{"learn":[3.097871596],"iteration":959,"passed_time":1.622714474,"remaining_time":0.0676131031},
{"learn":[3.097372213],"iteration":960,"passed_time":1.624367677,"remaining_time":0.06592126889},
{"learn":[3.095981813],"iteration":961,"passed_time":1.625813755,"remaining_time":0.06422133336},
{"learn":[3.095347452],"iteration":962,"passed_time":1.627343601,"remaining_time":0.06252514355},
{"learn":[3.094728409],"iteration":963,"passed_time":1.628945054,"remaining_time":0.06083197299},
{"learn":[3.094118537],"iteration":964,"passed_time":1.630371018,"remaining_time":0.05913262759},
{"learn":[3.093793695],"iteration":965,"passed_time":1.63180617,"remaining_time":0.0574341716},
{"learn":[3.092581602],"iteration":966,"passed_time":1.633226226,"remaining_time":0.05573574503},
{"learn":[3.091694202],"iteration":967,"passed_time":1.63464853,"remaining_time":0.05403796792},
{"learn":[3.090298312],"iteration":968,"passed_time":1.636293024,"remaining_time":0.05234786764},
{"learn":[3.090020107],"iteration":969,"passed_time":1.637771732,"remaining_time":0.05065273398},
{"learn":[3.088949869],"iteration":970,"passed_time":1.640101711,"remaining_time":0.04898347026},
{"learn":[3.086700204],"iteration":971,"passed_time":1.64149945,"remaining_time":0.04728599238},
{"learn":[3.086584317],"iteration":972,"passed_time":1.642958984,"remaining_time":0.04559084538},
{"learn":[3.084850742],"iteration":973,"passed_time":1.644475208,"remaining_time":0.04389769548},
{"learn":[3.084239948],"iteration":974,"passed_time":1.64596912,"remaining_time":0.04220433641},
{"learn":[3.082561673],"iteration":975,"passed_time":1.647424905,"remaining_time":0.0405104485},
{"learn":[3.07991814],"iteration":976,"passed_time":1.648940134,"remaining_time":0.03881844737},
{"learn":[3.079350277],"iteration":977,"passed_time":1.650307651,"remaining_time":0.03712348499},
{"learn":[3.077637462],"iteration":978,"passed_time":1.65187172,"remaining_time":0.03543340767},
{"learn":[3.076733301],"iteration":979,"passed_time":1.653408323,"remaining_time":0.033743027},
{"learn":[3.07594065],"iteration":980,"passed_time":1.655150055,"remaining_time":0.03205693276},
{"learn":[3.072594655],"iteration":981,"passed_time":1.656725458,"remaining_time":0.03036767642},
{"learn":[3.071977674],"iteration":982,"passed_time":1.658227498,"remaining_time":0.02867738298},
{"learn":[3.069532634],"iteration":983,"passed_time":1.659753962,"remaining_time":0.0269878693},
{"learn":[3.068870784],"iteration":984,"passed_time":1.661228098,"remaining_time":0.02529788982},
{"learn":[3.068801463],"iteration":985,"passed_time":1.662658563,"remaining_time":0.02360772807},
{"learn":[3.067433249],"iteration":986,"passed_time":1.664123505,"remaining_time":0.02191854667},
{"learn":[3.065611456],"iteration":987,"passed_time":1.665600184,"remaining_time":0.02022996175},
{"learn":[3.063039162],"iteration":988,"passed_time":1.66711006,"remaining_time":0.01854217458},
{"learn":[3.06177873],"iteration":989,"passed_time":1.669035651,"remaining_time":0.01685894597},
{"learn":[3.061689148],"iteration":990,"passed_time":1.670365721,"remaining_time":0.01516981987},
{"learn":[3.058984039],"iteration":991,"passed_time":1.671986479,"remaining_time":0.01348376193},
{"learn":[3.057492984],"iteration":992,"passed_time":1.673365325,"remaining_time":0.01179613018},
{"learn":[3.057290731],"iteration":993,"passed_time":1.674825848,"remaining_time":0.01010961277},
{"learn":[3.056068348],"iteration":994,"passed_time":1.676309324,"remaining_time":0.008423664947},
{"learn":[3.054987307],"iteration":995,"passed_time":1.677734358,"remaining_time":0.006737888988},
{"learn":[3.054200234],"iteration":996,"passed_time":1.67918678,"remaining_time":0.005052718496},
{"learn":[3.052732869],"iteration":997,"passed_time":1.680656688,"remaining_time":0.003368049475},
{"learn":[3.051787862],"iteration":998,"passed_time":1.682113759,"remaining_time":0.001683797557},
{"learn":[3.051366222],"iteration":999,"passed_time":1.683651654,"remaining_time":0}
]}